{"builtWith":"0.15.15","comments":[{"LineComment":" | D3 Force Engine Core"},{"LineComment":" |"},{"LineComment":" | This module provides D3-based force simulation functions."},{"LineComment":" | We use D3's force calculation algorithms but manage the simulation ourselves."},{"LineComment":" |"},{"LineComment":" | Key principle: Forces are just functions that mutate vx/vy on nodes."},{"LineComment":" | We control when they run and how alpha decays."}],"decls":[{"annotation":{"meta":null,"sourceSpan":{"end":[0,0],"start":[0,0]}},"bindType":"NonRec","expression":{"abstraction":{"annotation":{"meta":{"metaType":"IsForeign"},"sourceSpan":{"end":[247,28],"start":[247,3]}},"type":"Var","value":{"identifier":"bind","moduleName":["Control","Bind"]}},"annotation":{"meta":{"metaType":"IsSyntheticApp"},"sourceSpan":{"end":[247,28],"start":[247,3]}},"argument":{"annotation":{"meta":null,"sourceSpan":{"end":[0,0],"start":[0,0]}},"type":"Var","value":{"identifier":"bindEffect","moduleName":["Effect"]}},"type":"App"},"identifier":"bind"},{"annotation":{"meta":null,"sourceSpan":{"end":[0,0],"start":[0,0]}},"bindType":"NonRec","expression":{"abstraction":{"annotation":{"meta":{"metaType":"IsForeign"},"sourceSpan":{"end":[251,11],"start":[251,7]}},"type":"Var","value":{"identifier":"when","moduleName":["Control","Applicative"]}},"annotation":{"meta":{"metaType":"IsSyntheticApp"},"sourceSpan":{"end":[251,20],"start":[251,7]}},"argument":{"annotation":{"meta":null,"sourceSpan":{"end":[0,0],"start":[0,0]}},"type":"Var","value":{"identifier":"applicativeEffect","moduleName":["Effect"]}},"type":"App"},"identifier":"when"},{"annotation":{"meta":null,"sourceSpan":{"end":[0,0],"start":[0,0]}},"bindType":"NonRec","expression":{"abstraction":{"abstraction":{"annotation":{"meta":{"metaType":"IsForeign"},"sourceSpan":{"end":[255,32],"start":[255,3]}},"type":"Var","value":{"identifier":"discard","moduleName":["Control","Bind"]}},"annotation":{"meta":{"metaType":"IsSyntheticApp"},"sourceSpan":{"end":[255,32],"start":[255,3]}},"argument":{"annotation":{"meta":null,"sourceSpan":{"end":[0,0],"start":[0,0]}},"type":"Var","value":{"identifier":"discardUnit","moduleName":["Control","Bind"]}},"type":"App"},"annotation":{"meta":{"metaType":"IsSyntheticApp"},"sourceSpan":{"end":[255,32],"start":[255,3]}},"argument":{"annotation":{"meta":null,"sourceSpan":{"end":[0,0],"start":[0,0]}},"type":"Var","value":{"identifier":"bindEffect","moduleName":["Effect"]}},"type":"App"},"identifier":"discard"},{"annotation":{"meta":null,"sourceSpan":{"end":[0,0],"start":[0,0]}},"bindType":"NonRec","expression":{"abstraction":{"annotation":{"meta":{"metaType":"IsForeign"},"sourceSpan":{"end":[256,7],"start":[256,3]}},"type":"Var","value":{"identifier":"pure","moduleName":["Control","Applicative"]}},"annotation":{"meta":{"metaType":"IsSyntheticApp"},"sourceSpan":{"end":[256,7],"start":[256,3]}},"argument":{"annotation":{"meta":null,"sourceSpan":{"end":[0,0],"start":[0,0]}},"type":"Var","value":{"identifier":"applicativeEffect","moduleName":["Effect"]}},"type":"App"},"identifier":"pure"},{"annotation":{"meta":null,"sourceSpan":{"end":[0,0],"start":[0,0]}},"bindType":"NonRec","expression":{"abstraction":{"annotation":{"meta":{"metaType":"IsForeign"},"sourceSpan":{"end":[256,45],"start":[256,37]}},"type":"Var","value":{"identifier":"identity","moduleName":["Control","Category"]}},"annotation":{"meta":{"metaType":"IsSyntheticApp"},"sourceSpan":{"end":[256,45],"start":[256,37]}},"argument":{"annotation":{"meta":null,"sourceSpan":{"end":[0,0],"start":[0,0]}},"type":"Var","value":{"identifier":"categoryFn","moduleName":["Control","Category"]}},"type":"App"},"identifier":"identity"},{"annotation":{"meta":null,"sourceSpan":{"end":[0,0],"start":[0,0]}},"bindType":"NonRec","expression":{"abstraction":{"abstraction":{"annotation":{"meta":{"metaType":"IsForeign"},"sourceSpan":{"end":[212,32],"start":[212,28]}},"type":"Var","value":{"identifier":"for_","moduleName":["Data","Foldable"]}},"annotation":{"meta":{"metaType":"IsSyntheticApp"},"sourceSpan":{"end":[212,39],"start":[212,28]}},"argument":{"annotation":{"meta":null,"sourceSpan":{"end":[0,0],"start":[0,0]}},"type":"Var","value":{"identifier":"applicativeEffect","moduleName":["Effect"]}},"type":"App"},"annotation":{"meta":{"metaType":"IsSyntheticApp"},"sourceSpan":{"end":[212,39],"start":[212,28]}},"argument":{"annotation":{"meta":null,"sourceSpan":{"end":[0,0],"start":[0,0]}},"type":"Var","value":{"identifier":"foldableArray","moduleName":["Data","Foldable"]}},"type":"App"},"identifier":"for_"},{"annotation":{"meta":null,"sourceSpan":{"end":[264,48],"start":[264,1]}},"bindType":"NonRec","expression":{"annotation":{"meta":null,"sourceSpan":{"end":[264,48],"start":[264,1]}},"argument":"cancel","body":{"annotation":{"meta":null,"sourceSpan":{"end":[265,30],"start":[265,24]}},"type":"Var","value":{"identifier":"cancel","sourcePos":[265,1]}},"type":"Abs"},"identifier":"stopAnimation"},{"annotation":{"meta":null,"sourceSpan":{"end":[245,71],"start":[245,1]}},"bindType":"NonRec","expression":{"annotation":{"meta":null,"sourceSpan":{"end":[245,71],"start":[245,1]}},"argument":"onFrame","body":{"abstraction":{"abstraction":{"annotation":{"meta":null,"sourceSpan":{"end":[0,0],"start":[0,0]}},"type":"Var","value":{"identifier":"bind","moduleName":["PSD3","Kernel","D3","Core"]}},"annotation":{"meta":null,"sourceSpan":{"end":[247,28],"start":[247,3]}},"argument":{"annotation":{"meta":{"metaType":"IsForeign"},"sourceSpan":{"end":[247,28],"start":[247,16]}},"type":"Var","value":{"identifier":"newCancelRef","moduleName":["PSD3","Kernel","D3","Core"]}},"type":"App"},"annotation":{"meta":null,"sourceSpan":{"end":[247,28],"start":[247,3]}},"argument":{"annotation":{"meta":null,"sourceSpan":{"end":[247,28],"start":[247,3]}},"argument":"cancelRef","body":{"annotation":{"meta":null,"sourceSpan":{"end":[253,38],"start":[248,3]}},"binds":[{"bindType":"Rec","binds":[{"annotation":{"meta":null,"sourceSpan":{"end":[253,38],"start":[249,5]}},"expression":{"annotation":{"meta":null,"sourceSpan":{"end":[253,38],"start":[249,5]}},"argument":"timestamp","body":{"abstraction":{"abstraction":{"annotation":{"meta":null,"sourceSpan":{"end":[0,0],"start":[0,0]}},"type":"Var","value":{"identifier":"bind","moduleName":["PSD3","Kernel","D3","Core"]}},"annotation":{"meta":null,"sourceSpan":{"end":[250,36],"start":[250,7]}},"argument":{"abstraction":{"annotation":{"meta":null,"sourceSpan":{"end":[250,26],"start":[250,19]}},"type":"Var","value":{"identifier":"onFrame","sourcePos":[246,1]}},"annotation":{"meta":null,"sourceSpan":{"end":[250,36],"start":[250,19]}},"argument":{"annotation":{"meta":null,"sourceSpan":{"end":[250,36],"start":[250,27]}},"type":"Var","value":{"identifier":"timestamp","sourcePos":[249,5]}},"type":"App"},"type":"App"},"annotation":{"meta":null,"sourceSpan":{"end":[250,36],"start":[250,7]}},"argument":{"annotation":{"meta":null,"sourceSpan":{"end":[250,36],"start":[250,7]}},"argument":"continue","body":{"abstraction":{"abstraction":{"annotation":{"meta":null,"sourceSpan":{"end":[0,0],"start":[0,0]}},"type":"Var","value":{"identifier":"when","moduleName":["PSD3","Kernel","D3","Core"]}},"annotation":{"meta":null,"sourceSpan":{"end":[251,20],"start":[251,7]}},"argument":{"annotation":{"meta":null,"sourceSpan":{"end":[251,20],"start":[251,12]}},"type":"Var","value":{"identifier":"continue","sourcePos":[250,7]}},"type":"App"},"annotation":{"meta":null,"sourceSpan":{"end":[253,38],"start":[251,7]}},"argument":{"abstraction":{"abstraction":{"annotation":{"meta":null,"sourceSpan":{"end":[0,0],"start":[0,0]}},"type":"Var","value":{"identifier":"bind","moduleName":["PSD3","Kernel","D3","Core"]}},"annotation":{"meta":null,"sourceSpan":{"end":[252,46],"start":[252,9]}},"argument":{"abstraction":{"annotation":{"meta":{"metaType":"IsForeign"},"sourceSpan":{"end":[252,41],"start":[252,19]}},"type":"Var","value":{"identifier":"requestAnimationFrame_","moduleName":["PSD3","Kernel","D3","Core"]}},"annotation":{"meta":null,"sourceSpan":{"end":[252,46],"start":[252,19]}},"argument":{"annotation":{"meta":null,"sourceSpan":{"end":[252,46],"start":[252,42]}},"type":"Var","value":{"identifier":"loop","sourcePos":[249,5]}},"type":"App"},"type":"App"},"annotation":{"meta":null,"sourceSpan":{"end":[252,46],"start":[252,9]}},"argument":{"annotation":{"meta":null,"sourceSpan":{"end":[252,46],"start":[252,9]}},"argument":"cancel","body":{"abstraction":{"abstraction":{"annotation":{"meta":{"metaType":"IsForeign"},"sourceSpan":{"end":[253,21],"start":[253,9]}},"type":"Var","value":{"identifier":"setCancelRef","moduleName":["PSD3","Kernel","D3","Core"]}},"annotation":{"meta":null,"sourceSpan":{"end":[253,31],"start":[253,9]}},"argument":{"annotation":{"meta":null,"sourceSpan":{"end":[253,31],"start":[253,22]}},"type":"Var","value":{"identifier":"cancelRef","sourcePos":[247,3]}},"type":"App"},"annotation":{"meta":null,"sourceSpan":{"end":[253,38],"start":[253,9]}},"argument":{"annotation":{"meta":null,"sourceSpan":{"end":[253,38],"start":[253,32]}},"type":"Var","value":{"identifier":"cancel","sourcePos":[252,9]}},"type":"App"},"type":"Abs"},"type":"App"},"type":"App"},"type":"Abs"},"type":"App"},"type":"Abs"},"identifier":"loop"}]}],"expression":{"abstraction":{"abstraction":{"annotation":{"meta":null,"sourceSpan":{"end":[0,0],"start":[0,0]}},"type":"Var","value":{"identifier":"bind","moduleName":["PSD3","Kernel","D3","Core"]}},"annotation":{"meta":null,"sourceSpan":{"end":[254,40],"start":[254,3]}},"argument":{"abstraction":{"annotation":{"meta":{"metaType":"IsForeign"},"sourceSpan":{"end":[254,35],"start":[254,13]}},"type":"Var","value":{"identifier":"requestAnimationFrame_","moduleName":["PSD3","Kernel","D3","Core"]}},"annotation":{"meta":null,"sourceSpan":{"end":[254,40],"start":[254,13]}},"argument":{"annotation":{"meta":null,"sourceSpan":{"end":[254,40],"start":[254,36]}},"type":"Var","value":{"identifier":"loop","sourcePos":[249,5]}},"type":"App"},"type":"App"},"annotation":{"meta":null,"sourceSpan":{"end":[254,40],"start":[254,3]}},"argument":{"annotation":{"meta":null,"sourceSpan":{"end":[254,40],"start":[254,3]}},"argument":"cancel","body":{"abstraction":{"abstraction":{"annotation":{"meta":null,"sourceSpan":{"end":[0,0],"start":[0,0]}},"type":"Var","value":{"identifier":"discard","moduleName":["PSD3","Kernel","D3","Core"]}},"annotation":{"meta":null,"sourceSpan":{"end":[255,32],"start":[255,3]}},"argument":{"abstraction":{"abstraction":{"annotation":{"meta":{"metaType":"IsForeign"},"sourceSpan":{"end":[255,15],"start":[255,3]}},"type":"Var","value":{"identifier":"setCancelRef","moduleName":["PSD3","Kernel","D3","Core"]}},"annotation":{"meta":null,"sourceSpan":{"end":[255,25],"start":[255,3]}},"argument":{"annotation":{"meta":null,"sourceSpan":{"end":[255,25],"start":[255,16]}},"type":"Var","value":{"identifier":"cancelRef","sourcePos":[247,3]}},"type":"App"},"annotation":{"meta":null,"sourceSpan":{"end":[255,32],"start":[255,3]}},"argument":{"annotation":{"meta":null,"sourceSpan":{"end":[255,32],"start":[255,26]}},"type":"Var","value":{"identifier":"cancel","sourcePos":[254,3]}},"type":"App"},"type":"App"},"annotation":{"meta":null,"sourceSpan":{"end":[255,32],"start":[255,3]}},"argument":{"annotation":{"meta":null,"sourceSpan":{"end":[255,32],"start":[255,3]}},"argument":"$__unused","body":{"abstraction":{"annotation":{"meta":null,"sourceSpan":{"end":[0,0],"start":[0,0]}},"type":"Var","value":{"identifier":"pure","moduleName":["PSD3","Kernel","D3","Core"]}},"annotation":{"meta":null,"sourceSpan":{"end":[256,45],"start":[256,3]}},"argument":{"abstraction":{"abstraction":{"annotation":{"meta":null,"sourceSpan":{"end":[0,0],"start":[0,0]}},"type":"Var","value":{"identifier":"bind","moduleName":["PSD3","Kernel","D3","Core"]}},"annotation":{"meta":null,"sourceSpan":{"end":[256,45],"start":[256,3]}},"argument":{"abstraction":{"annotation":{"meta":{"metaType":"IsForeign"},"sourceSpan":{"end":[256,22],"start":[256,10]}},"type":"Var","value":{"identifier":"getCancelRef","moduleName":["PSD3","Kernel","D3","Core"]}},"annotation":{"meta":null,"sourceSpan":{"end":[256,32],"start":[256,10]}},"argument":{"annotation":{"meta":null,"sourceSpan":{"end":[256,32],"start":[256,23]}},"type":"Var","value":{"identifier":"cancelRef","sourcePos":[247,3]}},"type":"App"},"type":"App"},"annotation":{"meta":null,"sourceSpan":{"end":[256,45],"start":[256,3]}},"argument":{"annotation":{"meta":null,"sourceSpan":{"end":[0,0],"start":[0,0]}},"type":"Var","value":{"identifier":"identity","moduleName":["PSD3","Kernel","D3","Core"]}},"type":"App"},"type":"App"},"type":"Abs"},"type":"App"},"type":"Abs"},"type":"App"},"type":"Let"},"type":"Abs"},"type":"App"},"type":"Abs"},"identifier":"startAnimation"},{"annotation":{"meta":null,"sourceSpan":{"end":[294,58],"start":[294,1]}},"bindType":"NonRec","expression":{"annotation":{"meta":{"metaType":"IsForeign"},"sourceSpan":{"end":[295,47],"start":[295,25]}},"type":"Var","value":{"identifier":"querySelectorElements_","moduleName":["PSD3","Kernel","D3","Core"]}},"identifier":"querySelectorElements"},{"annotation":{"meta":null,"sourceSpan":{"end":[302,61],"start":[302,1]}},"bindType":"NonRec","expression":{"annotation":{"meta":{"metaType":"IsForeign"},"sourceSpan":{"end":[303,21],"start":[303,12]}},"type":"Var","value":{"identifier":"logNodes_","moduleName":["PSD3","Kernel","D3","Core"]}},"identifier":"logNodes"},{"annotation":{"meta":null,"sourceSpan":{"end":[215,71],"start":[215,1]}},"bindType":"NonRec","expression":{"annotation":{"meta":{"metaType":"IsForeign"},"sourceSpan":{"end":[216,41],"start":[216,22]}},"type":"Var","value":{"identifier":"integratePositions_","moduleName":["PSD3","Kernel","D3","Core"]}},"identifier":"integratePositions"},{"annotation":{"meta":null,"sourceSpan":{"end":[191,58],"start":[191,1]}},"bindType":"NonRec","expression":{"annotation":{"meta":{"metaType":"IsForeign"},"sourceSpan":{"end":[192,35],"start":[192,19]}},"type":"Var","value":{"identifier":"initializeNodes_","moduleName":["PSD3","Kernel","D3","Core"]}},"identifier":"initializeNodes"},{"annotation":{"meta":null,"sourceSpan":{"end":[199,127],"start":[199,1]}},"bindType":"NonRec","expression":{"annotation":{"meta":{"metaType":"IsForeign"},"sourceSpan":{"end":[200,43],"start":[200,23]}},"type":"Var","value":{"identifier":"initializeLinkForce_","moduleName":["PSD3","Kernel","D3","Core"]}},"identifier":"initializeLinkForce"},{"annotation":{"meta":null,"sourceSpan":{"end":[195,80],"start":[195,1]}},"bindType":"NonRec","expression":{"annotation":{"meta":{"metaType":"IsForeign"},"sourceSpan":{"end":[196,35],"start":[196,19]}},"type":"Var","value":{"identifier":"initializeForce_","moduleName":["PSD3","Kernel","D3","Core"]}},"identifier":"initializeForce"},{"annotation":{"meta":null,"sourceSpan":{"end":[219,61],"start":[219,1]}},"bindType":"NonRec","expression":{"annotation":{"meta":{"metaType":"IsForeign"},"sourceSpan":{"end":[220,25],"start":[220,14]}},"type":"Var","value":{"identifier":"decayAlpha_","moduleName":["PSD3","Kernel","D3","Core"]}},"identifier":"decayAlpha"},{"annotation":{"meta":null,"sourceSpan":{"end":[151,78],"start":[151,1]}},"bindType":"NonRec","expression":{"annotation":{"meta":{"metaType":"IsForeign"},"sourceSpan":{"end":[152,45],"start":[152,24]}},"type":"Var","value":{"identifier":"createRadialFiltered_","moduleName":["PSD3","Kernel","D3","Core"]}},"identifier":"createRadialFiltered"},{"annotation":{"meta":null,"sourceSpan":{"end":[139,44],"start":[139,1]}},"bindType":"NonRec","expression":{"annotation":{"meta":{"metaType":"IsForeign"},"sourceSpan":{"end":[140,29],"start":[140,16]}},"type":"Var","value":{"identifier":"createRadial_","moduleName":["PSD3","Kernel","D3","Core"]}},"identifier":"createRadial"},{"annotation":{"meta":null,"sourceSpan":{"end":[147,82],"start":[147,1]}},"bindType":"NonRec","expression":{"annotation":{"meta":{"metaType":"IsForeign"},"sourceSpan":{"end":[148,49],"start":[148,26]}},"type":"Var","value":{"identifier":"createManyBodyFiltered_","moduleName":["PSD3","Kernel","D3","Core"]}},"identifier":"createManyBodyFiltered"},{"annotation":{"meta":null,"sourceSpan":{"end":[115,48],"start":[115,1]}},"bindType":"NonRec","expression":{"annotation":{"meta":{"metaType":"IsForeign"},"sourceSpan":{"end":[116,33],"start":[116,18]}},"type":"Var","value":{"identifier":"createManyBody_","moduleName":["PSD3","Kernel","D3","Core"]}},"identifier":"createManyBody"},{"annotation":{"meta":null,"sourceSpan":{"end":[167,72],"start":[167,1]}},"bindType":"NonRec","expression":{"annotation":{"meta":{"metaType":"IsForeign"},"sourceSpan":{"end":[168,39],"start":[168,21]}},"type":"Var","value":{"identifier":"createLinkDynamic_","moduleName":["PSD3","Kernel","D3","Core"]}},"identifier":"createLinkDynamic"},{"annotation":{"meta":null,"sourceSpan":{"end":[123,40],"start":[123,1]}},"bindType":"NonRec","expression":{"annotation":{"meta":{"metaType":"IsForeign"},"sourceSpan":{"end":[124,25],"start":[124,14]}},"type":"Var","value":{"identifier":"createLink_","moduleName":["PSD3","Kernel","D3","Core"]}},"identifier":"createLink"},{"annotation":{"meta":null,"sourceSpan":{"end":[179,42],"start":[179,1]}},"bindType":"NonRec","expression":{"annotation":{"meta":{"metaType":"IsForeign"},"sourceSpan":{"end":[180,37],"start":[180,20]}},"type":"Var","value":{"identifier":"createForceYGrid_","moduleName":["PSD3","Kernel","D3","Core"]}},"identifier":"createForceYGrid"},{"annotation":{"meta":null,"sourceSpan":{"end":[163,76],"start":[163,1]}},"bindType":"NonRec","expression":{"annotation":{"meta":{"metaType":"IsForeign"},"sourceSpan":{"end":[164,43],"start":[164,23]}},"type":"Var","value":{"identifier":"createForceYDynamic_","moduleName":["PSD3","Kernel","D3","Core"]}},"identifier":"createForceYDynamic"},{"annotation":{"meta":null,"sourceSpan":{"end":[135,44],"start":[135,1]}},"bindType":"NonRec","expression":{"annotation":{"meta":{"metaType":"IsForeign"},"sourceSpan":{"end":[136,29],"start":[136,16]}},"type":"Var","value":{"identifier":"createForceY_","moduleName":["PSD3","Kernel","D3","Core"]}},"identifier":"createForceY"},{"annotation":{"meta":null,"sourceSpan":{"end":[175,42],"start":[175,1]}},"bindType":"NonRec","expression":{"annotation":{"meta":{"metaType":"IsForeign"},"sourceSpan":{"end":[176,37],"start":[176,20]}},"type":"Var","value":{"identifier":"createForceXGrid_","moduleName":["PSD3","Kernel","D3","Core"]}},"identifier":"createForceXGrid"},{"annotation":{"meta":null,"sourceSpan":{"end":[159,76],"start":[159,1]}},"bindType":"NonRec","expression":{"annotation":{"meta":{"metaType":"IsForeign"},"sourceSpan":{"end":[160,43],"start":[160,23]}},"type":"Var","value":{"identifier":"createForceXDynamic_","moduleName":["PSD3","Kernel","D3","Core"]}},"identifier":"createForceXDynamic"},{"annotation":{"meta":null,"sourceSpan":{"end":[131,44],"start":[131,1]}},"bindType":"NonRec","expression":{"annotation":{"meta":{"metaType":"IsForeign"},"sourceSpan":{"end":[132,29],"start":[132,16]}},"type":"Var","value":{"identifier":"createForceX_","moduleName":["PSD3","Kernel","D3","Core"]}},"identifier":"createForceX"},{"annotation":{"meta":null,"sourceSpan":{"end":[183,60],"start":[183,1]}},"bindType":"NonRec","expression":{"annotation":{"meta":{"metaType":"IsForeign"},"sourceSpan":{"end":[184,39],"start":[184,21]}},"type":"Var","value":{"identifier":"createCollideGrid_","moduleName":["PSD3","Kernel","D3","Core"]}},"identifier":"createCollideGrid"},{"annotation":{"meta":null,"sourceSpan":{"end":[155,78],"start":[155,1]}},"bindType":"NonRec","expression":{"annotation":{"meta":{"metaType":"IsForeign"},"sourceSpan":{"end":[156,45],"start":[156,24]}},"type":"Var","value":{"identifier":"createCollideDynamic_","moduleName":["PSD3","Kernel","D3","Core"]}},"identifier":"createCollideDynamic"},{"annotation":{"meta":null,"sourceSpan":{"end":[119,46],"start":[119,1]}},"bindType":"NonRec","expression":{"annotation":{"meta":{"metaType":"IsForeign"},"sourceSpan":{"end":[120,31],"start":[120,17]}},"type":"Var","value":{"identifier":"createCollide_","moduleName":["PSD3","Kernel","D3","Core"]}},"identifier":"createCollide"},{"annotation":{"meta":null,"sourceSpan":{"end":[127,44],"start":[127,1]}},"bindType":"NonRec","expression":{"annotation":{"meta":{"metaType":"IsForeign"},"sourceSpan":{"end":[128,29],"start":[128,16]}},"type":"Var","value":{"identifier":"createCenter_","moduleName":["PSD3","Kernel","D3","Core"]}},"identifier":"createCenter"},{"annotation":{"meta":null,"sourceSpan":{"end":[284,65],"start":[284,1]}},"bindType":"NonRec","expression":{"annotation":{"meta":{"metaType":"IsForeign"},"sourceSpan":{"end":[285,39],"start":[285,21]}},"type":"Var","value":{"identifier":"attachPinningDrag_","moduleName":["PSD3","Kernel","D3","Core"]}},"identifier":"attachPinningDrag"},{"annotation":{"meta":null,"sourceSpan":{"end":[280,83],"start":[280,1]}},"bindType":"NonRec","expression":{"annotation":{"meta":{"metaType":"IsForeign"},"sourceSpan":{"end":[281,55],"start":[281,29]}},"type":"Var","value":{"identifier":"attachGroupDragWithReheat_","moduleName":["PSD3","Kernel","D3","Core"]}},"identifier":"attachGroupDragWithReheat"},{"annotation":{"meta":null,"sourceSpan":{"end":[276,68],"start":[276,1]}},"bindType":"NonRec","expression":{"annotation":{"meta":{"metaType":"IsForeign"},"sourceSpan":{"end":[277,45],"start":[277,24]}},"type":"Var","value":{"identifier":"attachDragWithReheat_","moduleName":["PSD3","Kernel","D3","Core"]}},"identifier":"attachDragWithReheat"},{"annotation":{"meta":null,"sourceSpan":{"end":[207,51],"start":[207,1]}},"bindType":"NonRec","expression":{"annotation":{"meta":{"metaType":"IsForeign"},"sourceSpan":{"end":[208,25],"start":[208,14]}},"type":"Var","value":{"identifier":"applyForce_","moduleName":["PSD3","Kernel","D3","Core"]}},"identifier":"applyForce"},{"annotation":{"meta":null,"sourceSpan":{"end":[211,58],"start":[211,1]}},"bindType":"NonRec","expression":{"annotation":{"meta":null,"sourceSpan":{"end":[211,58],"start":[211,1]}},"argument":"forces","body":{"annotation":{"meta":null,"sourceSpan":{"end":[211,58],"start":[211,1]}},"argument":"alpha","body":{"abstraction":{"abstraction":{"annotation":{"meta":null,"sourceSpan":{"end":[0,0],"start":[0,0]}},"type":"Var","value":{"identifier":"for_","moduleName":["PSD3","Kernel","D3","Core"]}},"annotation":{"meta":null,"sourceSpan":{"end":[212,39],"start":[212,28]}},"argument":{"annotation":{"meta":null,"sourceSpan":{"end":[212,39],"start":[212,33]}},"type":"Var","value":{"identifier":"forces","sourcePos":[212,1]}},"type":"App"},"annotation":{"meta":null,"sourceSpan":{"end":[212,64],"start":[212,28]}},"argument":{"annotation":{"meta":null,"sourceSpan":{"end":[212,64],"start":[212,40]}},"argument":"f","body":{"abstraction":{"abstraction":{"annotation":{"meta":null,"sourceSpan":{"end":[212,56],"start":[212,46]}},"type":"Var","value":{"identifier":"applyForce","moduleName":["PSD3","Kernel","D3","Core"]}},"annotation":{"meta":null,"sourceSpan":{"end":[212,58],"start":[212,46]}},"argument":{"annotation":{"meta":null,"sourceSpan":{"end":[212,58],"start":[212,57]}},"type":"Var","value":{"identifier":"f","sourcePos":[212,41]}},"type":"App"},"annotation":{"meta":null,"sourceSpan":{"end":[212,64],"start":[212,46]}},"argument":{"annotation":{"meta":null,"sourceSpan":{"end":[212,64],"start":[212,59]}},"type":"Var","value":{"identifier":"alpha","sourcePos":[212,1]}},"type":"App"},"type":"Abs"},"type":"App"},"type":"Abs"},"type":"Abs"},"identifier":"applyForces"},{"annotation":{"meta":null,"sourceSpan":{"end":[232,19],"start":[223,1]}},"bindType":"NonRec","expression":{"annotation":{"meta":null,"sourceSpan":{"end":[232,19],"start":[223,1]}},"argument":"params","body":{"abstraction":{"abstraction":{"annotation":{"meta":null,"sourceSpan":{"end":[0,0],"start":[0,0]}},"type":"Var","value":{"identifier":"discard","moduleName":["PSD3","Kernel","D3","Core"]}},"annotation":{"meta":null,"sourceSpan":{"end":[234,41],"start":[234,3]}},"argument":{"abstraction":{"abstraction":{"annotation":{"meta":null,"sourceSpan":{"end":[234,14],"start":[234,3]}},"type":"Var","value":{"identifier":"applyForces","moduleName":["PSD3","Kernel","D3","Core"]}},"annotation":{"meta":null,"sourceSpan":{"end":[234,28],"start":[234,3]}},"argument":{"annotation":{"meta":null,"sourceSpan":{"end":[234,28],"start":[234,15]}},"expression":{"annotation":{"meta":null,"sourceSpan":{"end":[234,21],"start":[234,15]}},"type":"Var","value":{"identifier":"params","sourcePos":[233,1]}},"fieldName":"forces","type":"Accessor"},"type":"App"},"annotation":{"meta":null,"sourceSpan":{"end":[234,41],"start":[234,3]}},"argument":{"annotation":{"meta":null,"sourceSpan":{"end":[234,41],"start":[234,29]}},"expression":{"annotation":{"meta":null,"sourceSpan":{"end":[234,35],"start":[234,29]}},"type":"Var","value":{"identifier":"params","sourcePos":[233,1]}},"fieldName":"alpha","type":"Accessor"},"type":"App"},"type":"App"},"annotation":{"meta":null,"sourceSpan":{"end":[234,41],"start":[234,3]}},"argument":{"annotation":{"meta":null,"sourceSpan":{"end":[234,41],"start":[234,3]}},"argument":"$__unused","body":{"abstraction":{"abstraction":{"annotation":{"meta":null,"sourceSpan":{"end":[0,0],"start":[0,0]}},"type":"Var","value":{"identifier":"discard","moduleName":["PSD3","Kernel","D3","Core"]}},"annotation":{"meta":null,"sourceSpan":{"end":[235,55],"start":[235,3]}},"argument":{"abstraction":{"abstraction":{"annotation":{"meta":null,"sourceSpan":{"end":[235,21],"start":[235,3]}},"type":"Var","value":{"identifier":"integratePositions","moduleName":["PSD3","Kernel","D3","Core"]}},"annotation":{"meta":null,"sourceSpan":{"end":[235,34],"start":[235,3]}},"argument":{"annotation":{"meta":null,"sourceSpan":{"end":[235,34],"start":[235,22]}},"expression":{"annotation":{"meta":null,"sourceSpan":{"end":[235,28],"start":[235,22]}},"type":"Var","value":{"identifier":"params","sourcePos":[233,1]}},"fieldName":"nodes","type":"Accessor"},"type":"App"},"annotation":{"meta":null,"sourceSpan":{"end":[235,55],"start":[235,3]}},"argument":{"annotation":{"meta":null,"sourceSpan":{"end":[235,55],"start":[235,35]}},"expression":{"annotation":{"meta":null,"sourceSpan":{"end":[235,41],"start":[235,35]}},"type":"Var","value":{"identifier":"params","sourcePos":[233,1]}},"fieldName":"velocityDecay","type":"Accessor"},"type":"App"},"type":"App"},"annotation":{"meta":null,"sourceSpan":{"end":[235,55],"start":[235,3]}},"argument":{"annotation":{"meta":null,"sourceSpan":{"end":[235,55],"start":[235,3]}},"argument":"$__unused","body":{"abstraction":{"annotation":{"meta":null,"sourceSpan":{"end":[0,0],"start":[0,0]}},"type":"Var","value":{"identifier":"pure","moduleName":["PSD3","Kernel","D3","Core"]}},"annotation":{"meta":null,"sourceSpan":{"end":[236,86],"start":[236,3]}},"argument":{"abstraction":{"abstraction":{"abstraction":{"abstraction":{"annotation":{"meta":null,"sourceSpan":{"end":[236,20],"start":[236,10]}},"type":"Var","value":{"identifier":"decayAlpha","moduleName":["PSD3","Kernel","D3","Core"]}},"annotation":{"meta":null,"sourceSpan":{"end":[236,33],"start":[236,10]}},"argument":{"annotation":{"meta":null,"sourceSpan":{"end":[236,33],"start":[236,21]}},"expression":{"annotation":{"meta":null,"sourceSpan":{"end":[236,27],"start":[236,21]}},"type":"Var","value":{"identifier":"params","sourcePos":[233,1]}},"fieldName":"alpha","type":"Accessor"},"type":"App"},"annotation":{"meta":null,"sourceSpan":{"end":[236,49],"start":[236,10]}},"argument":{"annotation":{"meta":null,"sourceSpan":{"end":[236,49],"start":[236,34]}},"expression":{"annotation":{"meta":null,"sourceSpan":{"end":[236,40],"start":[236,34]}},"type":"Var","value":{"identifier":"params","sourcePos":[233,1]}},"fieldName":"alphaMin","type":"Accessor"},"type":"App"},"annotation":{"meta":null,"sourceSpan":{"end":[236,67],"start":[236,10]}},"argument":{"annotation":{"meta":null,"sourceSpan":{"end":[236,67],"start":[236,50]}},"expression":{"annotation":{"meta":null,"sourceSpan":{"end":[236,56],"start":[236,50]}},"type":"Var","value":{"identifier":"params","sourcePos":[233,1]}},"fieldName":"alphaDecay","type":"Accessor"},"type":"App"},"annotation":{"meta":null,"sourceSpan":{"end":[236,86],"start":[236,10]}},"argument":{"annotation":{"meta":null,"sourceSpan":{"end":[236,86],"start":[236,68]}},"expression":{"annotation":{"meta":null,"sourceSpan":{"end":[236,74],"start":[236,68]}},"type":"Var","value":{"identifier":"params","sourcePos":[233,1]}},"fieldName":"alphaTarget","type":"Accessor"},"type":"App"},"type":"App"},"type":"Abs"},"type":"App"},"type":"Abs"},"type":"App"},"type":"Abs"},"identifier":"simulationTick"}],"exports":["createManyBody","createCollide","createLink","createCenter","createForceX","createForceY","createRadial","createManyBodyFiltered","createRadialFiltered","createCollideDynamic","createForceXDynamic","createForceYDynamic","createLinkDynamic","createForceXGrid","createForceYGrid","createCollideGrid","initializeNodes","initializeForce","initializeLinkForce","applyForce","applyForces","integratePositions","decayAlpha","simulationTick","startAnimation","stopAnimation","attachDragWithReheat","attachGroupDragWithReheat","attachPinningDrag","querySelectorElements","logNodes"],"foreign":["createManyBody_","createCollide_","createLink_","createCenter_","createForceX_","createForceY_","createRadial_","createManyBodyFiltered_","createRadialFiltered_","createCollideDynamic_","createForceXDynamic_","createForceYDynamic_","createLinkDynamic_","createForceXGrid_","createForceYGrid_","createCollideGrid_","initializeNodes_","initializeForce_","initializeLinkForce_","applyForce_","integratePositions_","decayAlpha_","requestAnimationFrame_","logNodes_","newCancelRef","setCancelRef","getCancelRef","attachDragWithReheat_","attachGroupDragWithReheat_","attachPinningDrag_","querySelectorElements_"],"imports":[{"annotation":{"meta":null,"sourceSpan":{"end":[303,21],"start":[8,1]}},"moduleName":["Control","Applicative"]},{"annotation":{"meta":null,"sourceSpan":{"end":[303,21],"start":[8,1]}},"moduleName":["Control","Bind"]},{"annotation":{"meta":null,"sourceSpan":{"end":[303,21],"start":[8,1]}},"moduleName":["Control","Category"]},{"annotation":{"meta":null,"sourceSpan":{"end":[303,21],"start":[8,1]}},"moduleName":["Data","Foldable"]},{"annotation":{"meta":null,"sourceSpan":{"end":[303,21],"start":[8,1]}},"moduleName":["Data","Function"]},{"annotation":{"meta":null,"sourceSpan":{"end":[56,31],"start":[56,1]}},"moduleName":["Data","Traversable"]},{"annotation":{"meta":null,"sourceSpan":{"end":[303,21],"start":[8,1]}},"moduleName":["Effect"]},{"annotation":{"meta":null,"sourceSpan":{"end":[303,21],"start":[8,1]}},"moduleName":["PSD3","Kernel","D3","Core"]},{"annotation":{"meta":null,"sourceSpan":{"end":[58,257],"start":[58,1]}},"moduleName":["PSD3","Kernel","D3","Types"]},{"annotation":{"meta":null,"sourceSpan":{"end":[54,15],"start":[54,1]}},"moduleName":["Prelude"]},{"annotation":{"meta":null,"sourceSpan":{"end":[303,21],"start":[8,1]}},"moduleName":["Prim"]},{"annotation":{"meta":null,"sourceSpan":{"end":[59,33],"start":[59,1]}},"moduleName":["Web","DOM","Element"]}],"moduleName":["PSD3","Kernel","D3","Core"],"modulePath":"../purescript-psd3-d3-kernel/src/PSD3/Kernel/D3/Core.purs","reExports":{},"sourceSpan":{"end":[303,21],"start":[8,1]}}