{"builtWith":"0.15.15","comments":[{"LineComment":" | PSD3.TreeDSL - Finally Tagless Tree Building"},{"LineComment":" |"},{"LineComment":" | This module provides the extensible, typeclass-based API for building"},{"LineComment":" | visualization trees. Unlike the concrete `Tree` ADT, this approach allows"},{"LineComment":" | extensions without modifying the core library."},{"LineComment":" |"},{"LineComment":" | ## Design"},{"LineComment":" |"},{"LineComment":" | `TreeDSL` is a typeclass parameterized by a type constructor `tree`:"},{"LineComment":" |"},{"LineComment":" | ```purescript"},{"LineComment":" | class TreeDSL tree where"},{"LineComment":" |   named :: ElementType -> String -> Array (Attribute d) -> tree d"},{"LineComment":" |   ..."},{"LineComment":" | ```"},{"LineComment":" |"},{"LineComment":" | Different implementations can provide different behaviors:"},{"LineComment":" | - `Tree` (from PSD3.AST) - builds a concrete AST for later interpretation"},{"LineComment":" | - Direct DOM interpreter - renders immediately"},{"LineComment":" | - Mermaid interpreter - generates diagram code"},{"LineComment":" |"},{"LineComment":" | ## Extension"},{"LineComment":" |"},{"LineComment":" | New features are added via subclasses:"},{"LineComment":" |"},{"LineComment":" | ```purescript"},{"LineComment":" | class TreeDSL tree <= ShapeTreeDSL tree where"},{"LineComment":" |   fromSpec :: (d -> ShapeSpec d) -> tree d"},{"LineComment":" | ```"},{"LineComment":" |"},{"LineComment":" | Extensions don't require modifying the core `TreeDSL` class."},{"LineComment":" |"}],"decls":[{"annotation":{"meta":null,"sourceSpan":{"end":[0,0],"start":[0,0]}},"bindType":"NonRec","expression":{"abstraction":{"annotation":{"meta":{"metaType":"IsForeign"},"sourceSpan":{"end":[277,30],"start":[277,28]}},"type":"Var","value":{"identifier":"append","moduleName":["Data","Semigroup"]}},"annotation":{"meta":{"metaType":"IsSyntheticApp"},"sourceSpan":{"end":[277,74],"start":[277,22]}},"argument":{"annotation":{"meta":null,"sourceSpan":{"end":[0,0],"start":[0,0]}},"type":"Var","value":{"identifier":"semigroupArray","moduleName":["Data","Semigroup"]}},"type":"App"},"identifier":"append"},{"annotation":{"meta":{"metaType":"IsTypeClassConstructor"},"sourceSpan":{"end":[263,18],"start":[93,1]}},"bindType":"NonRec","expression":{"annotation":{"meta":{"metaType":"IsNewtype"},"sourceSpan":{"end":[263,18],"start":[93,1]}},"argument":"x","body":{"annotation":{"meta":null,"sourceSpan":{"end":[263,18],"start":[93,1]}},"type":"Var","value":{"identifier":"x","sourcePos":[0,0]}},"type":"Abs"},"identifier":"TreeDSL$Dict"},{"annotation":{"meta":null,"sourceSpan":{"end":[148,18],"start":[144,3]}},"bindType":"NonRec","expression":{"annotation":{"meta":null,"sourceSpan":{"end":[148,18],"start":[144,3]}},"argument":"dict","body":{"annotation":{"meta":null,"sourceSpan":{"end":[148,18],"start":[144,3]}},"caseAlternatives":[{"binders":[{"annotation":{"meta":{"metaType":"IsNewtype"},"sourceSpan":{"end":[148,18],"start":[144,3]}},"binderType":"ConstructorBinder","binders":[{"annotation":{"meta":null,"sourceSpan":{"end":[148,18],"start":[144,3]}},"binderType":"VarBinder","identifier":"v"}],"constructorName":{"identifier":"TreeDSL$Dict","moduleName":["PSD3","TreeDSL"]},"typeName":{"identifier":"TreeDSL$Dict","moduleName":["PSD3","TreeDSL"]}}],"expression":{"annotation":{"meta":null,"sourceSpan":{"end":[148,18],"start":[144,3]}},"expression":{"annotation":{"meta":null,"sourceSpan":{"end":[148,18],"start":[144,3]}},"type":"Var","value":{"identifier":"v","sourcePos":[0,0]}},"fieldName":"withChildren","type":"Accessor"},"isGuarded":false}],"caseExpressions":[{"annotation":{"meta":null,"sourceSpan":{"end":[148,18],"start":[144,3]}},"type":"Var","value":{"identifier":"dict","sourcePos":[0,0]}}],"type":"Case"},"type":"Abs"},"identifier":"withChildren"},{"annotation":{"meta":null,"sourceSpan":{"end":[136,18],"start":[132,3]}},"bindType":"NonRec","expression":{"annotation":{"meta":null,"sourceSpan":{"end":[136,18],"start":[132,3]}},"argument":"dict","body":{"annotation":{"meta":null,"sourceSpan":{"end":[136,18],"start":[132,3]}},"caseAlternatives":[{"binders":[{"annotation":{"meta":{"metaType":"IsNewtype"},"sourceSpan":{"end":[136,18],"start":[132,3]}},"binderType":"ConstructorBinder","binders":[{"annotation":{"meta":null,"sourceSpan":{"end":[136,18],"start":[132,3]}},"binderType":"VarBinder","identifier":"v"}],"constructorName":{"identifier":"TreeDSL$Dict","moduleName":["PSD3","TreeDSL"]},"typeName":{"identifier":"TreeDSL$Dict","moduleName":["PSD3","TreeDSL"]}}],"expression":{"annotation":{"meta":null,"sourceSpan":{"end":[136,18],"start":[132,3]}},"expression":{"annotation":{"meta":null,"sourceSpan":{"end":[136,18],"start":[132,3]}},"type":"Var","value":{"identifier":"v","sourcePos":[0,0]}},"fieldName":"withChild","type":"Accessor"},"isGuarded":false}],"caseExpressions":[{"annotation":{"meta":null,"sourceSpan":{"end":[136,18],"start":[132,3]}},"type":"Var","value":{"identifier":"dict","sourcePos":[0,0]}}],"type":"Case"},"type":"Abs"},"identifier":"withChild"},{"annotation":{"meta":null,"sourceSpan":{"end":[160,18],"start":[156,3]}},"bindType":"NonRec","expression":{"annotation":{"meta":null,"sourceSpan":{"end":[160,18],"start":[156,3]}},"argument":"dict","body":{"annotation":{"meta":null,"sourceSpan":{"end":[160,18],"start":[156,3]}},"caseAlternatives":[{"binders":[{"annotation":{"meta":{"metaType":"IsNewtype"},"sourceSpan":{"end":[160,18],"start":[156,3]}},"binderType":"ConstructorBinder","binders":[{"annotation":{"meta":null,"sourceSpan":{"end":[160,18],"start":[156,3]}},"binderType":"VarBinder","identifier":"v"}],"constructorName":{"identifier":"TreeDSL$Dict","moduleName":["PSD3","TreeDSL"]},"typeName":{"identifier":"TreeDSL$Dict","moduleName":["PSD3","TreeDSL"]}}],"expression":{"annotation":{"meta":null,"sourceSpan":{"end":[160,18],"start":[156,3]}},"expression":{"annotation":{"meta":null,"sourceSpan":{"end":[160,18],"start":[156,3]}},"type":"Var","value":{"identifier":"v","sourcePos":[0,0]}},"fieldName":"withBehaviors","type":"Accessor"},"isGuarded":false}],"caseExpressions":[{"annotation":{"meta":null,"sourceSpan":{"end":[160,18],"start":[156,3]}},"type":"Var","value":{"identifier":"dict","sourcePos":[0,0]}}],"type":"Case"},"type":"Abs"},"identifier":"withBehaviors"},{"annotation":{"meta":null,"sourceSpan":{"end":[237,23],"start":[229,3]}},"bindType":"NonRec","expression":{"annotation":{"meta":null,"sourceSpan":{"end":[237,23],"start":[229,3]}},"argument":"dict","body":{"annotation":{"meta":null,"sourceSpan":{"end":[237,23],"start":[229,3]}},"caseAlternatives":[{"binders":[{"annotation":{"meta":{"metaType":"IsNewtype"},"sourceSpan":{"end":[237,23],"start":[229,3]}},"binderType":"ConstructorBinder","binders":[{"annotation":{"meta":null,"sourceSpan":{"end":[237,23],"start":[229,3]}},"binderType":"VarBinder","identifier":"v"}],"constructorName":{"identifier":"TreeDSL$Dict","moduleName":["PSD3","TreeDSL"]},"typeName":{"identifier":"TreeDSL$Dict","moduleName":["PSD3","TreeDSL"]}}],"expression":{"annotation":{"meta":null,"sourceSpan":{"end":[237,23],"start":[229,3]}},"expression":{"annotation":{"meta":null,"sourceSpan":{"end":[237,23],"start":[229,3]}},"type":"Var","value":{"identifier":"v","sourcePos":[0,0]}},"fieldName":"updateNestedJoin","type":"Accessor"},"isGuarded":false}],"caseExpressions":[{"annotation":{"meta":null,"sourceSpan":{"end":[237,23],"start":[229,3]}},"type":"Var","value":{"identifier":"dict","sourcePos":[0,0]}}],"type":"Case"},"type":"Abs"},"identifier":"updateNestedJoin"},{"annotation":{"meta":null,"sourceSpan":{"end":[223,18],"start":[212,3]}},"bindType":"NonRec","expression":{"annotation":{"meta":null,"sourceSpan":{"end":[223,18],"start":[212,3]}},"argument":"dict","body":{"annotation":{"meta":null,"sourceSpan":{"end":[223,18],"start":[212,3]}},"caseAlternatives":[{"binders":[{"annotation":{"meta":{"metaType":"IsNewtype"},"sourceSpan":{"end":[223,18],"start":[212,3]}},"binderType":"ConstructorBinder","binders":[{"annotation":{"meta":null,"sourceSpan":{"end":[223,18],"start":[212,3]}},"binderType":"VarBinder","identifier":"v"}],"constructorName":{"identifier":"TreeDSL$Dict","moduleName":["PSD3","TreeDSL"]},"typeName":{"identifier":"TreeDSL$Dict","moduleName":["PSD3","TreeDSL"]}}],"expression":{"annotation":{"meta":null,"sourceSpan":{"end":[223,18],"start":[212,3]}},"expression":{"annotation":{"meta":null,"sourceSpan":{"end":[223,18],"start":[212,3]}},"type":"Var","value":{"identifier":"v","sourcePos":[0,0]}},"fieldName":"updateJoin","type":"Accessor"},"isGuarded":false}],"caseExpressions":[{"annotation":{"meta":null,"sourceSpan":{"end":[223,18],"start":[212,3]}},"type":"Var","value":{"identifier":"dict","sourcePos":[0,0]}}],"type":"Case"},"type":"Abs"},"identifier":"updateJoin"},{"annotation":{"meta":null,"sourceSpan":{"end":[294,72],"start":[294,1]}},"bindType":"NonRec","expression":{"abstraction":{"annotation":{"meta":{"metaType":"IsForeign"},"sourceSpan":{"end":[295,20],"start":[295,12]}},"type":"Var","value":{"identifier":"identity","moduleName":["Control","Category"]}},"annotation":{"meta":{"metaType":"IsSyntheticApp"},"sourceSpan":{"end":[295,20],"start":[295,12]}},"argument":{"annotation":{"meta":null,"sourceSpan":{"end":[0,0],"start":[0,0]}},"type":"Var","value":{"identifier":"categoryFn","moduleName":["Control","Category"]}},"type":"App"},"identifier":"siblings"},{"annotation":{"meta":null,"sourceSpan":{"end":[197,23],"start":[190,3]}},"bindType":"NonRec","expression":{"annotation":{"meta":null,"sourceSpan":{"end":[197,23],"start":[190,3]}},"argument":"dict","body":{"annotation":{"meta":null,"sourceSpan":{"end":[197,23],"start":[190,3]}},"caseAlternatives":[{"binders":[{"annotation":{"meta":{"metaType":"IsNewtype"},"sourceSpan":{"end":[197,23],"start":[190,3]}},"binderType":"ConstructorBinder","binders":[{"annotation":{"meta":null,"sourceSpan":{"end":[197,23],"start":[190,3]}},"binderType":"VarBinder","identifier":"v"}],"constructorName":{"identifier":"TreeDSL$Dict","moduleName":["PSD3","TreeDSL"]},"typeName":{"identifier":"TreeDSL$Dict","moduleName":["PSD3","TreeDSL"]}}],"expression":{"annotation":{"meta":null,"sourceSpan":{"end":[197,23],"start":[190,3]}},"expression":{"annotation":{"meta":null,"sourceSpan":{"end":[197,23],"start":[190,3]}},"type":"Var","value":{"identifier":"v","sourcePos":[0,0]}},"fieldName":"nestedJoin","type":"Accessor"},"isGuarded":false}],"caseExpressions":[{"annotation":{"meta":null,"sourceSpan":{"end":[197,23],"start":[190,3]}},"type":"Var","value":{"identifier":"dict","sourcePos":[0,0]}}],"type":"Case"},"type":"Abs"},"identifier":"nestedJoin"},{"annotation":{"meta":null,"sourceSpan":{"end":[109,18],"start":[104,3]}},"bindType":"NonRec","expression":{"annotation":{"meta":null,"sourceSpan":{"end":[109,18],"start":[104,3]}},"argument":"dict","body":{"annotation":{"meta":null,"sourceSpan":{"end":[109,18],"start":[104,3]}},"caseAlternatives":[{"binders":[{"annotation":{"meta":{"metaType":"IsNewtype"},"sourceSpan":{"end":[109,18],"start":[104,3]}},"binderType":"ConstructorBinder","binders":[{"annotation":{"meta":null,"sourceSpan":{"end":[109,18],"start":[104,3]}},"binderType":"VarBinder","identifier":"v"}],"constructorName":{"identifier":"TreeDSL$Dict","moduleName":["PSD3","TreeDSL"]},"typeName":{"identifier":"TreeDSL$Dict","moduleName":["PSD3","TreeDSL"]}}],"expression":{"annotation":{"meta":null,"sourceSpan":{"end":[109,18],"start":[104,3]}},"expression":{"annotation":{"meta":null,"sourceSpan":{"end":[109,18],"start":[104,3]}},"type":"Var","value":{"identifier":"v","sourcePos":[0,0]}},"fieldName":"named","type":"Accessor"},"isGuarded":false}],"caseExpressions":[{"annotation":{"meta":null,"sourceSpan":{"end":[109,18],"start":[104,3]}},"type":"Var","value":{"identifier":"dict","sourcePos":[0,0]}}],"type":"Case"},"type":"Abs"},"identifier":"named"},{"annotation":{"meta":null,"sourceSpan":{"end":[263,18],"start":[259,3]}},"bindType":"NonRec","expression":{"annotation":{"meta":null,"sourceSpan":{"end":[263,18],"start":[259,3]}},"argument":"dict","body":{"annotation":{"meta":null,"sourceSpan":{"end":[263,18],"start":[259,3]}},"caseAlternatives":[{"binders":[{"annotation":{"meta":{"metaType":"IsNewtype"},"sourceSpan":{"end":[263,18],"start":[259,3]}},"binderType":"ConstructorBinder","binders":[{"annotation":{"meta":null,"sourceSpan":{"end":[263,18],"start":[259,3]}},"binderType":"VarBinder","identifier":"v"}],"constructorName":{"identifier":"TreeDSL$Dict","moduleName":["PSD3","TreeDSL"]},"typeName":{"identifier":"TreeDSL$Dict","moduleName":["PSD3","TreeDSL"]}}],"expression":{"annotation":{"meta":null,"sourceSpan":{"end":[263,18],"start":[259,3]}},"expression":{"annotation":{"meta":null,"sourceSpan":{"end":[263,18],"start":[259,3]}},"type":"Var","value":{"identifier":"v","sourcePos":[0,0]}},"fieldName":"localCoordSpace","type":"Accessor"},"isGuarded":false}],"caseExpressions":[{"annotation":{"meta":null,"sourceSpan":{"end":[263,18],"start":[259,3]}},"type":"Var","value":{"identifier":"dict","sourcePos":[0,0]}}],"type":"Case"},"type":"Abs"},"identifier":"localCoordSpace"},{"annotation":{"meta":null,"sourceSpan":{"end":[286,16],"start":[280,1]}},"bindType":"NonRec","expression":{"annotation":{"meta":null,"sourceSpan":{"end":[286,16],"start":[280,1]}},"argument":"dictTreeDSL","body":{"annotation":{"meta":null,"sourceSpan":{"end":[0,0],"start":[0,0]}},"binds":[{"annotation":{"meta":null,"sourceSpan":{"end":[0,0],"start":[0,0]}},"bindType":"NonRec","expression":{"abstraction":{"annotation":{"meta":null,"sourceSpan":{"end":[287,43],"start":[287,28]}},"type":"Var","value":{"identifier":"localCoordSpace","moduleName":["PSD3","TreeDSL"]}},"annotation":{"meta":{"metaType":"IsSyntheticApp"},"sourceSpan":{"end":[287,80],"start":[287,28]}},"argument":{"annotation":{"meta":null,"sourceSpan":{"end":[0,0],"start":[0,0]}},"type":"Var","value":{"identifier":"dictTreeDSL","sourcePos":[0,0]}},"type":"App"},"identifier":"localCoordSpace1"}],"expression":{"annotation":{"meta":null,"sourceSpan":{"end":[286,16],"start":[280,1]}},"argument":"w","body":{"annotation":{"meta":null,"sourceSpan":{"end":[286,16],"start":[280,1]}},"argument":"h","body":{"abstraction":{"annotation":{"meta":null,"sourceSpan":{"end":[0,0],"start":[0,0]}},"type":"Var","value":{"identifier":"localCoordSpace1","sourcePos":[0,0]}},"annotation":{"meta":null,"sourceSpan":{"end":[287,80],"start":[287,28]}},"argument":{"annotation":{"meta":null,"sourceSpan":{"end":[287,80],"start":[287,44]}},"type":"Literal","value":{"literalType":"ObjectLiteral","value":[["scaleX",{"annotation":{"meta":null,"sourceSpan":{"end":[287,61],"start":[287,54]}},"argument":"v","body":{"annotation":{"meta":null,"sourceSpan":{"end":[287,61],"start":[287,60]}},"type":"Var","value":{"identifier":"w","sourcePos":[287,1]}},"type":"Abs"}],["scaleY",{"annotation":{"meta":null,"sourceSpan":{"end":[287,78],"start":[287,71]}},"argument":"v","body":{"annotation":{"meta":null,"sourceSpan":{"end":[287,78],"start":[287,77]}},"type":"Var","value":{"identifier":"h","sourcePos":[287,1]}},"type":"Abs"}]]}},"type":"App"},"type":"Abs"},"type":"Abs"},"type":"Let"},"type":"Abs"},"identifier":"localCoordSpaceFixed"},{"annotation":{"meta":null,"sourceSpan":{"end":[178,18],"start":[172,3]}},"bindType":"NonRec","expression":{"annotation":{"meta":null,"sourceSpan":{"end":[178,18],"start":[172,3]}},"argument":"dict","body":{"annotation":{"meta":null,"sourceSpan":{"end":[178,18],"start":[172,3]}},"caseAlternatives":[{"binders":[{"annotation":{"meta":{"metaType":"IsNewtype"},"sourceSpan":{"end":[178,18],"start":[172,3]}},"binderType":"ConstructorBinder","binders":[{"annotation":{"meta":null,"sourceSpan":{"end":[178,18],"start":[172,3]}},"binderType":"VarBinder","identifier":"v"}],"constructorName":{"identifier":"TreeDSL$Dict","moduleName":["PSD3","TreeDSL"]},"typeName":{"identifier":"TreeDSL$Dict","moduleName":["PSD3","TreeDSL"]}}],"expression":{"annotation":{"meta":null,"sourceSpan":{"end":[178,18],"start":[172,3]}},"expression":{"annotation":{"meta":null,"sourceSpan":{"end":[178,18],"start":[172,3]}},"type":"Var","value":{"identifier":"v","sourcePos":[0,0]}},"fieldName":"joinData","type":"Accessor"},"isGuarded":false}],"caseExpressions":[{"annotation":{"meta":null,"sourceSpan":{"end":[178,18],"start":[172,3]}},"type":"Var","value":{"identifier":"dict","sourcePos":[0,0]}}],"type":"Case"},"type":"Abs"},"identifier":"joinData"},{"annotation":{"meta":null,"sourceSpan":{"end":[124,18],"start":[120,3]}},"bindType":"NonRec","expression":{"annotation":{"meta":null,"sourceSpan":{"end":[124,18],"start":[120,3]}},"argument":"dict","body":{"annotation":{"meta":null,"sourceSpan":{"end":[124,18],"start":[120,3]}},"caseAlternatives":[{"binders":[{"annotation":{"meta":{"metaType":"IsNewtype"},"sourceSpan":{"end":[124,18],"start":[120,3]}},"binderType":"ConstructorBinder","binders":[{"annotation":{"meta":null,"sourceSpan":{"end":[124,18],"start":[120,3]}},"binderType":"VarBinder","identifier":"v"}],"constructorName":{"identifier":"TreeDSL$Dict","moduleName":["PSD3","TreeDSL"]},"typeName":{"identifier":"TreeDSL$Dict","moduleName":["PSD3","TreeDSL"]}}],"expression":{"annotation":{"meta":null,"sourceSpan":{"end":[124,18],"start":[120,3]}},"expression":{"annotation":{"meta":null,"sourceSpan":{"end":[124,18],"start":[120,3]}},"type":"Var","value":{"identifier":"v","sourcePos":[0,0]}},"fieldName":"elem","type":"Accessor"},"isGuarded":false}],"caseExpressions":[{"annotation":{"meta":null,"sourceSpan":{"end":[124,18],"start":[120,3]}},"type":"Var","value":{"identifier":"dict","sourcePos":[0,0]}}],"type":"Case"},"type":"Abs"},"identifier":"elem"},{"annotation":{"meta":null,"sourceSpan":{"end":[254,18],"start":[251,3]}},"bindType":"NonRec","expression":{"annotation":{"meta":null,"sourceSpan":{"end":[254,18],"start":[251,3]}},"argument":"dict","body":{"annotation":{"meta":null,"sourceSpan":{"end":[254,18],"start":[251,3]}},"caseAlternatives":[{"binders":[{"annotation":{"meta":{"metaType":"IsNewtype"},"sourceSpan":{"end":[254,18],"start":[251,3]}},"binderType":"ConstructorBinder","binders":[{"annotation":{"meta":null,"sourceSpan":{"end":[254,18],"start":[251,3]}},"binderType":"VarBinder","identifier":"v"}],"constructorName":{"identifier":"TreeDSL$Dict","moduleName":["PSD3","TreeDSL"]},"typeName":{"identifier":"TreeDSL$Dict","moduleName":["PSD3","TreeDSL"]}}],"expression":{"annotation":{"meta":null,"sourceSpan":{"end":[254,18],"start":[251,3]}},"expression":{"annotation":{"meta":null,"sourceSpan":{"end":[254,18],"start":[251,3]}},"type":"Var","value":{"identifier":"v","sourcePos":[0,0]}},"fieldName":"conditionalRender","type":"Accessor"},"isGuarded":false}],"caseExpressions":[{"annotation":{"meta":null,"sourceSpan":{"end":[254,18],"start":[251,3]}},"type":"Var","value":{"identifier":"dict","sourcePos":[0,0]}}],"type":"Case"},"type":"Abs"},"identifier":"conditionalRender"},{"annotation":{"meta":null,"sourceSpan":{"end":[275,16],"start":[270,1]}},"bindType":"NonRec","expression":{"annotation":{"meta":null,"sourceSpan":{"end":[275,16],"start":[270,1]}},"argument":"dictTreeDSL","body":{"annotation":{"meta":null,"sourceSpan":{"end":[0,0],"start":[0,0]}},"binds":[{"annotation":{"meta":null,"sourceSpan":{"end":[0,0],"start":[0,0]}},"bindType":"NonRec","expression":{"abstraction":{"annotation":{"meta":null,"sourceSpan":{"end":[277,20],"start":[277,3]}},"type":"Var","value":{"identifier":"conditionalRender","moduleName":["PSD3","TreeDSL"]}},"annotation":{"meta":{"metaType":"IsSyntheticApp"},"sourceSpan":{"end":[277,75],"start":[277,3]}},"argument":{"annotation":{"meta":null,"sourceSpan":{"end":[0,0],"start":[0,0]}},"type":"Var","value":{"identifier":"dictTreeDSL","sourcePos":[0,0]}},"type":"App"},"identifier":"conditionalRender1"}],"expression":{"annotation":{"meta":null,"sourceSpan":{"end":[275,16],"start":[270,1]}},"argument":"cases","body":{"annotation":{"meta":null,"sourceSpan":{"end":[275,16],"start":[270,1]}},"argument":"fallback","body":{"abstraction":{"annotation":{"meta":null,"sourceSpan":{"end":[0,0],"start":[0,0]}},"type":"Var","value":{"identifier":"conditionalRender1","sourcePos":[0,0]}},"annotation":{"meta":null,"sourceSpan":{"end":[277,75],"start":[277,3]}},"argument":{"abstraction":{"abstraction":{"annotation":{"meta":null,"sourceSpan":{"end":[0,0],"start":[0,0]}},"type":"Var","value":{"identifier":"append","moduleName":["PSD3","TreeDSL"]}},"annotation":{"meta":null,"sourceSpan":{"end":[277,74],"start":[277,22]}},"argument":{"annotation":{"meta":null,"sourceSpan":{"end":[277,27],"start":[277,22]}},"type":"Var","value":{"identifier":"cases","sourcePos":[276,1]}},"type":"App"},"annotation":{"meta":null,"sourceSpan":{"end":[277,74],"start":[277,22]}},"argument":{"annotation":{"meta":null,"sourceSpan":{"end":[277,74],"start":[277,31]}},"type":"Literal","value":{"literalType":"ArrayLiteral","value":[{"annotation":{"meta":null,"sourceSpan":{"end":[277,73],"start":[277,32]}},"type":"Literal","value":{"literalType":"ObjectLiteral","value":[["predicate",{"annotation":{"meta":null,"sourceSpan":{"end":[277,55],"start":[277,45]}},"argument":"v","body":{"annotation":{"meta":null,"sourceSpan":{"end":[277,55],"start":[277,51]}},"type":"Literal","value":{"literalType":"BooleanLiteral","value":true}},"type":"Abs"}],["spec",{"annotation":{"meta":null,"sourceSpan":{"end":[277,71],"start":[277,63]}},"type":"Var","value":{"identifier":"fallback","sourcePos":[276,1]}}]]}}]}},"type":"App"},"type":"App"},"type":"Abs"},"type":"Abs"},"type":"Let"},"type":"Abs"},"identifier":"conditionalRenderOr"},{"annotation":{"meta":null,"sourceSpan":{"end":[290,76],"start":[290,1]}},"bindType":"NonRec","expression":{"annotation":{"meta":null,"sourceSpan":{"end":[290,76],"start":[290,1]}},"argument":"left","body":{"annotation":{"meta":null,"sourceSpan":{"end":[290,76],"start":[290,1]}},"argument":"right","body":{"annotation":{"meta":null,"sourceSpan":{"end":[291,34],"start":[291,21]}},"type":"Literal","value":{"literalType":"ArrayLiteral","value":[{"annotation":{"meta":null,"sourceSpan":{"end":[291,26],"start":[291,22]}},"type":"Var","value":{"identifier":"left","sourcePos":[291,1]}},{"annotation":{"meta":null,"sourceSpan":{"end":[291,33],"start":[291,28]}},"type":"Var","value":{"identifier":"right","sourcePos":[291,1]}}]}},"type":"Abs"},"type":"Abs"},"identifier":"beside"}],"exports":["named","elem","withChild","withChildren","withBehaviors","joinData","nestedJoin","updateJoin","updateNestedJoin","conditionalRender","conditionalRenderOr","localCoordSpace","localCoordSpaceFixed","beside","siblings"],"foreign":[],"imports":[{"annotation":{"meta":null,"sourceSpan":{"end":[302,22],"start":[33,1]}},"moduleName":["Control","Category"]},{"annotation":{"meta":null,"sourceSpan":{"end":[61,26],"start":[61,1]}},"moduleName":["Data","Maybe"]},{"annotation":{"meta":null,"sourceSpan":{"end":[302,22],"start":[33,1]}},"moduleName":["Data","Semigroup"]},{"annotation":{"meta":null,"sourceSpan":{"end":[62,43],"start":[62,1]}},"moduleName":["PSD3","Internal","Attribute"]},{"annotation":{"meta":null,"sourceSpan":{"end":[63,47],"start":[63,1]}},"moduleName":["PSD3","Internal","Behavior","Types"]},{"annotation":{"meta":null,"sourceSpan":{"end":[64,51],"start":[64,1]}},"moduleName":["PSD3","Internal","Selection","Types"]},{"annotation":{"meta":null,"sourceSpan":{"end":[65,57],"start":[65,1]}},"moduleName":["PSD3","Internal","Transition","Types"]},{"annotation":{"meta":null,"sourceSpan":{"end":[302,22],"start":[33,1]}},"moduleName":["PSD3","TreeDSL"]},{"annotation":{"meta":null,"sourceSpan":{"end":[59,15],"start":[59,1]}},"moduleName":["Prelude"]},{"annotation":{"meta":null,"sourceSpan":{"end":[302,22],"start":[33,1]}},"moduleName":["Prim"]}],"moduleName":["PSD3","TreeDSL"],"modulePath":"../purescript-psd3-selection/src/PSD3/TreeDSL.purs","reExports":{},"sourceSpan":{"end":[302,22],"start":[33,1]}}