{"builtWith":"0.15.15","comments":[{"LineComment":" | Transition Engine"},{"LineComment":" |"},{"LineComment":" | A tick-driven transition engine for managing animated state changes."},{"LineComment":" | This provides a framework-agnostic way to animate values over time,"},{"LineComment":" | suitable for both Halogen and React integrations."},{"LineComment":" |"},{"LineComment":" | Key concepts:"},{"LineComment":" | - **TransitionSpec**: Defines what to animate (from/to values, duration, easing)"},{"LineComment":" | - **TransitionState**: Current state of an in-flight transition"},{"LineComment":" | - **TransitionGroup**: Manages multiple coordinated transitions"},{"LineComment":" |"},{"LineComment":" | Design goals:"},{"LineComment":" | - Pure, deterministic state updates (no side effects)"},{"LineComment":" | - Works with any tick source (simulation tick, RAF, manual)"},{"LineComment":" | - Composable with existing PSD3 infrastructure"},{"LineComment":" |"},{"LineComment":" | Usage:"},{"LineComment":" | ```purescript"},{"LineComment":" | import PSD3.Transition.Engine as E"},{"LineComment":" | import PSD3.Transition.Easing (EasingType(..))"},{"LineComment":" |"},{"LineComment":" | -- Create a transition spec"},{"LineComment":" | let spec = E.transition"},{"LineComment":" |       { from: 0.0, to: 100.0 }"},{"LineComment":" |       { duration: 500.0, easing: QuadOut }"},{"LineComment":" |"},{"LineComment":" | -- Start the transition"},{"LineComment":" | let state = E.start spec"},{"LineComment":" |"},{"LineComment":" | -- In tick handler: advance by delta (milliseconds)"},{"LineComment":" | let state' = E.tick 16.67 state"},{"LineComment":" |"},{"LineComment":" | -- Get current value"},{"LineComment":" | let current = E.currentValue state'"},{"LineComment":" | ```"}],"decls":[{"annotation":{"meta":null,"sourceSpan":{"end":[0,0],"start":[0,0]}},"bindType":"NonRec","expression":{"abstraction":{"annotation":{"meta":{"metaType":"IsForeign"},"sourceSpan":{"end":[173,33],"start":[173,32]}},"type":"Var","value":{"identifier":"add","moduleName":["Data","Semiring"]}},"annotation":{"meta":{"metaType":"IsSyntheticApp"},"sourceSpan":{"end":[173,39],"start":[173,18]}},"argument":{"annotation":{"meta":null,"sourceSpan":{"end":[0,0],"start":[0,0]}},"type":"Var","value":{"identifier":"semiringNumber","moduleName":["Data","Semiring"]}},"type":"App"},"identifier":"add"},{"annotation":{"meta":null,"sourceSpan":{"end":[0,0],"start":[0,0]}},"bindType":"NonRec","expression":{"abstraction":{"annotation":{"meta":{"metaType":"IsForeign"},"sourceSpan":{"end":[174,27],"start":[174,24]}},"type":"Var","value":{"identifier":"max","moduleName":["Data","Ord"]}},"annotation":{"meta":{"metaType":"IsSyntheticApp"},"sourceSpan":{"end":[174,31],"start":[174,24]}},"argument":{"annotation":{"meta":null,"sourceSpan":{"end":[0,0],"start":[0,0]}},"type":"Var","value":{"identifier":"ordNumber","moduleName":["Data","Ord"]}},"type":"App"},"identifier":"max"},{"annotation":{"meta":null,"sourceSpan":{"end":[0,0],"start":[0,0]}},"bindType":"NonRec","expression":{"abstraction":{"annotation":{"meta":{"metaType":"IsForeign"},"sourceSpan":{"end":[174,45],"start":[174,44]}},"type":"Var","value":{"identifier":"sub","moduleName":["Data","Ring"]}},"annotation":{"meta":{"metaType":"IsSyntheticApp"},"sourceSpan":{"end":[174,69],"start":[174,33]}},"argument":{"annotation":{"meta":null,"sourceSpan":{"end":[0,0],"start":[0,0]}},"type":"Var","value":{"identifier":"ringNumber","moduleName":["Data","Ring"]}},"type":"App"},"identifier":"sub"},{"annotation":{"meta":null,"sourceSpan":{"end":[0,0],"start":[0,0]}},"bindType":"NonRec","expression":{"abstraction":{"annotation":{"meta":{"metaType":"IsForeign"},"sourceSpan":{"end":[175,37],"start":[175,36]}},"type":"Var","value":{"identifier":"div","moduleName":["Data","EuclideanRing"]}},"annotation":{"meta":{"metaType":"IsSyntheticApp"},"sourceSpan":{"end":[175,64],"start":[175,19]}},"argument":{"annotation":{"meta":null,"sourceSpan":{"end":[0,0],"start":[0,0]}},"type":"Var","value":{"identifier":"euclideanRingNumber","moduleName":["Data","EuclideanRing"]}},"type":"App"},"identifier":"div"},{"annotation":{"meta":null,"sourceSpan":{"end":[0,0],"start":[0,0]}},"bindType":"NonRec","expression":{"abstraction":{"annotation":{"meta":{"metaType":"IsForeign"},"sourceSpan":{"end":[176,26],"start":[176,23]}},"type":"Var","value":{"identifier":"min","moduleName":["Data","Ord"]}},"annotation":{"meta":{"metaType":"IsSyntheticApp"},"sourceSpan":{"end":[176,30],"start":[176,23]}},"argument":{"annotation":{"meta":null,"sourceSpan":{"end":[0,0],"start":[0,0]}},"type":"Var","value":{"identifier":"ordNumber","moduleName":["Data","Ord"]}},"type":"App"},"identifier":"min"},{"annotation":{"meta":null,"sourceSpan":{"end":[0,0],"start":[0,0]}},"bindType":"NonRec","expression":{"abstraction":{"annotation":{"meta":{"metaType":"IsForeign"},"sourceSpan":{"end":[268,36],"start":[268,35]}},"type":"Var","value":{"identifier":"mul","moduleName":["Data","Semiring"]}},"annotation":{"meta":{"metaType":"IsSyntheticApp"},"sourceSpan":{"end":[268,49],"start":[268,24]}},"argument":{"annotation":{"meta":null,"sourceSpan":{"end":[0,0],"start":[0,0]}},"type":"Var","value":{"identifier":"semiringNumber","moduleName":["Data","Semiring"]}},"type":"App"},"identifier":"mul"},{"annotation":{"meta":null,"sourceSpan":{"end":[0,0],"start":[0,0]}},"bindType":"NonRec","expression":{"abstraction":{"annotation":{"meta":{"metaType":"IsForeign"},"sourceSpan":{"end":[264,6],"start":[264,3]}},"type":"Var","value":{"identifier":"map","moduleName":["Data","Functor"]}},"annotation":{"meta":{"metaType":"IsSyntheticApp"},"sourceSpan":{"end":[264,13],"start":[264,3]}},"argument":{"annotation":{"meta":null,"sourceSpan":{"end":[0,0],"start":[0,0]}},"type":"Var","value":{"identifier":"functorArray","moduleName":["Data","Functor"]}},"type":"App"},"identifier":"map"},{"annotation":{"meta":null,"sourceSpan":{"end":[0,0],"start":[0,0]}},"bindType":"NonRec","expression":{"abstraction":{"annotation":{"meta":{"metaType":"IsForeign"},"sourceSpan":{"end":[264,28],"start":[264,27]}},"type":"Var","value":{"identifier":"sub","moduleName":["Data","Ring"]}},"annotation":{"meta":{"metaType":"IsSyntheticApp"},"sourceSpan":{"end":[264,30],"start":[264,21]}},"argument":{"annotation":{"meta":null,"sourceSpan":{"end":[0,0],"start":[0,0]}},"type":"Var","value":{"identifier":"ringInt","moduleName":["Data","Ring"]}},"type":"App"},"identifier":"sub1"},{"annotation":{"meta":null,"sourceSpan":{"end":[0,0],"start":[0,0]}},"bindType":"NonRec","expression":{"abstraction":{"annotation":{"meta":{"metaType":"IsForeign"},"sourceSpan":{"end":[202,19],"start":[202,17]}},"type":"Var","value":{"identifier":"greaterThanOrEq","moduleName":["Data","Ord"]}},"annotation":{"meta":{"metaType":"IsSyntheticApp"},"sourceSpan":{"end":[202,74],"start":[202,3]}},"argument":{"annotation":{"meta":null,"sourceSpan":{"end":[0,0],"start":[0,0]}},"type":"Var","value":{"identifier":"ordNumber","moduleName":["Data","Ord"]}},"type":"App"},"identifier":"greaterThanOrEq"},{"annotation":{"meta":null,"sourceSpan":{"end":[0,0],"start":[0,0]}},"bindType":"NonRec","expression":{"abstraction":{"abstraction":{"annotation":{"meta":{"metaType":"IsForeign"},"sourceSpan":{"end":[348,26],"start":[348,19]}},"type":"Var","value":{"identifier":"maximum","moduleName":["Data","Foldable"]}},"annotation":{"meta":{"metaType":"IsSyntheticApp"},"sourceSpan":{"end":[348,26],"start":[348,19]}},"argument":{"annotation":{"meta":null,"sourceSpan":{"end":[0,0],"start":[0,0]}},"type":"Var","value":{"identifier":"ordNumber","moduleName":["Data","Ord"]}},"type":"App"},"annotation":{"meta":{"metaType":"IsSyntheticApp"},"sourceSpan":{"end":[348,26],"start":[348,19]}},"argument":{"annotation":{"meta":null,"sourceSpan":{"end":[0,0],"start":[0,0]}},"type":"Var","value":{"identifier":"foldableArray","moduleName":["Data","Foldable"]}},"type":"App"},"identifier":"maximum"},{"annotation":{"meta":null,"sourceSpan":{"end":[0,0],"start":[0,0]}},"bindType":"NonRec","expression":{"abstraction":{"abstraction":{"annotation":{"meta":{"metaType":"IsForeign"},"sourceSpan":{"end":[343,6],"start":[343,3]}},"type":"Var","value":{"identifier":"all","moduleName":["Data","Foldable"]}},"annotation":{"meta":{"metaType":"IsSyntheticApp"},"sourceSpan":{"end":[343,33],"start":[343,3]}},"argument":{"annotation":{"meta":null,"sourceSpan":{"end":[0,0],"start":[0,0]}},"type":"Var","value":{"identifier":"foldableArray","moduleName":["Data","Foldable"]}},"type":"App"},"annotation":{"meta":{"metaType":"IsSyntheticApp"},"sourceSpan":{"end":[343,33],"start":[343,3]}},"argument":{"annotation":{"meta":null,"sourceSpan":{"end":[0,0],"start":[0,0]}},"type":"Var","value":{"identifier":"heytingAlgebraBoolean","moduleName":["Data","HeytingAlgebra"]}},"type":"App"},"identifier":"all"},{"annotation":{"meta":null,"sourceSpan":{"end":[217,4],"start":[215,1]}},"bindType":"NonRec","expression":{"annotation":{"meta":{"metaType":"IsNewtype"},"sourceSpan":{"end":[217,4],"start":[215,1]}},"argument":"x","body":{"annotation":{"meta":null,"sourceSpan":{"end":[217,4],"start":[215,1]}},"type":"Var","value":{"identifier":"x","sourcePos":[0,0]}},"type":"Abs"},"identifier":"TransitionGroup"},{"annotation":{"meta":null,"sourceSpan":{"end":[306,4],"start":[304,1]}},"bindType":"NonRec","expression":{"annotation":{"meta":{"metaType":"IsNewtype"},"sourceSpan":{"end":[306,4],"start":[304,1]}},"argument":"x","body":{"annotation":{"meta":null,"sourceSpan":{"end":[306,4],"start":[304,1]}},"type":"Var","value":{"identifier":"x","sourcePos":[0,0]}},"type":"Abs"},"identifier":"IndexedTransitionGroup"},{"annotation":{"meta":null,"sourceSpan":{"end":[249,76],"start":[249,1]}},"bindType":"NonRec","expression":{"annotation":{"meta":null,"sourceSpan":{"end":[249,76],"start":[249,1]}},"argument":"delay","body":{"annotation":{"meta":null,"sourceSpan":{"end":[249,76],"start":[249,1]}},"argument":"spec","body":{"annotation":{"meta":null,"sourceSpan":{"end":[251,50],"start":[251,3]}},"binds":[{"annotation":{"meta":null,"sourceSpan":{"end":[251,50],"start":[250,1]}},"bindType":"NonRec","expression":{"annotation":{"meta":null,"sourceSpan":{"end":[251,7],"start":[251,3]}},"type":"Var","value":{"identifier":"spec","sourcePos":[250,1]}},"identifier":"v"}],"expression":{"annotation":{"meta":null,"sourceSpan":{"end":[251,50],"start":[251,3]}},"copy":["from","to","interpolate"],"expression":{"annotation":{"meta":null,"sourceSpan":{"end":[0,0],"start":[0,0]}},"type":"Var","value":{"identifier":"v","sourcePos":[250,1]}},"type":"ObjectUpdate","updates":[["config",{"annotation":{"meta":null,"sourceSpan":{"end":[251,48],"start":[251,19]}},"binds":[{"annotation":{"meta":null,"sourceSpan":{"end":[251,50],"start":[250,1]}},"bindType":"NonRec","expression":{"annotation":{"meta":null,"sourceSpan":{"end":[251,30],"start":[251,19]}},"expression":{"annotation":{"meta":null,"sourceSpan":{"end":[251,23],"start":[251,19]}},"type":"Var","value":{"identifier":"spec","sourcePos":[250,1]}},"fieldName":"config","type":"Accessor"},"identifier":"v1"}],"expression":{"annotation":{"meta":null,"sourceSpan":{"end":[251,48],"start":[251,19]}},"copy":["duration","easing"],"expression":{"annotation":{"meta":null,"sourceSpan":{"end":[0,0],"start":[0,0]}},"type":"Var","value":{"identifier":"v1","sourcePos":[250,1]}},"type":"ObjectUpdate","updates":[["delay",{"annotation":{"meta":null,"sourceSpan":{"end":[251,46],"start":[251,41]}},"type":"Var","value":{"identifier":"delay","sourcePos":[250,1]}}]]},"type":"Let"}]]},"type":"Let"},"type":"Abs"},"type":"Abs"},"identifier":"withDelay"},{"annotation":{"meta":null,"sourceSpan":{"end":[137,22],"start":[132,1]}},"bindType":"NonRec","expression":{"annotation":{"meta":null,"sourceSpan":{"end":[137,22],"start":[132,1]}},"argument":"interpolate","body":{"annotation":{"meta":null,"sourceSpan":{"end":[137,22],"start":[132,1]}},"argument":"values","body":{"annotation":{"meta":null,"sourceSpan":{"end":[137,22],"start":[132,1]}},"argument":"config","body":{"annotation":{"meta":null,"sourceSpan":{"end":[143,4],"start":[139,3]}},"type":"Literal","value":{"literalType":"ObjectLiteral","value":[["from",{"annotation":{"meta":null,"sourceSpan":{"end":[139,22],"start":[139,11]}},"expression":{"annotation":{"meta":null,"sourceSpan":{"end":[139,17],"start":[139,11]}},"type":"Var","value":{"identifier":"values","sourcePos":[138,1]}},"fieldName":"from","type":"Accessor"}],["to",{"annotation":{"meta":null,"sourceSpan":{"end":[140,18],"start":[140,9]}},"expression":{"annotation":{"meta":null,"sourceSpan":{"end":[140,15],"start":[140,9]}},"type":"Var","value":{"identifier":"values","sourcePos":[138,1]}},"fieldName":"to","type":"Accessor"}],["interpolate",{"annotation":{"meta":null,"sourceSpan":{"end":[141,16],"start":[141,5]}},"type":"Var","value":{"identifier":"interpolate","sourcePos":[138,1]}}],["config",{"annotation":{"meta":null,"sourceSpan":{"end":[142,11],"start":[142,5]}},"type":"Var","value":{"identifier":"config","sourcePos":[138,1]}}]]}},"type":"Abs"},"type":"Abs"},"type":"Abs"},"identifier":"transitionWith"},{"annotation":{"meta":null,"sourceSpan":{"end":[119,27],"start":[116,1]}},"bindType":"NonRec","expression":{"annotation":{"meta":null,"sourceSpan":{"end":[119,27],"start":[116,1]}},"argument":"values","body":{"annotation":{"meta":null,"sourceSpan":{"end":[119,27],"start":[116,1]}},"argument":"opts","body":{"annotation":{"meta":null,"sourceSpan":{"end":[129,4],"start":[121,3]}},"type":"Literal","value":{"literalType":"ObjectLiteral","value":[["from",{"annotation":{"meta":null,"sourceSpan":{"end":[121,22],"start":[121,11]}},"expression":{"annotation":{"meta":null,"sourceSpan":{"end":[121,17],"start":[121,11]}},"type":"Var","value":{"identifier":"values","sourcePos":[120,1]}},"fieldName":"from","type":"Accessor"}],["to",{"annotation":{"meta":null,"sourceSpan":{"end":[122,18],"start":[122,9]}},"expression":{"annotation":{"meta":null,"sourceSpan":{"end":[122,15],"start":[122,9]}},"type":"Var","value":{"identifier":"values","sourcePos":[120,1]}},"fieldName":"to","type":"Accessor"}],["interpolate",{"annotation":{"meta":{"metaType":"IsForeign"},"sourceSpan":{"end":[123,22],"start":[123,18]}},"type":"Var","value":{"identifier":"lerp","moduleName":["PSD3","Transition","Tick"]}}],["config",{"annotation":{"meta":null,"sourceSpan":{"end":[128,8],"start":[125,7]}},"type":"Literal","value":{"literalType":"ObjectLiteral","value":[["duration",{"annotation":{"meta":null,"sourceSpan":{"end":[125,32],"start":[125,19]}},"expression":{"annotation":{"meta":null,"sourceSpan":{"end":[125,23],"start":[125,19]}},"type":"Var","value":{"identifier":"opts","sourcePos":[120,1]}},"fieldName":"duration","type":"Accessor"}],["easing",{"annotation":{"meta":null,"sourceSpan":{"end":[126,28],"start":[126,17]}},"expression":{"annotation":{"meta":null,"sourceSpan":{"end":[126,21],"start":[126,17]}},"type":"Var","value":{"identifier":"opts","sourcePos":[120,1]}},"fieldName":"easing","type":"Accessor"}],["delay",{"annotation":{"meta":null,"sourceSpan":{"end":[127,19],"start":[127,16]}},"type":"Literal","value":{"literalType":"NumberLiteral","value":0}}]]}}]]}},"type":"Abs"},"type":"Abs"},"identifier":"transition"},{"annotation":{"meta":null,"sourceSpan":{"end":[170,75],"start":[170,1]}},"bindType":"NonRec","expression":{"annotation":{"meta":null,"sourceSpan":{"end":[170,75],"start":[170,1]}},"argument":"delta","body":{"annotation":{"meta":null,"sourceSpan":{"end":[170,75],"start":[170,1]}},"argument":"state","body":{"annotation":{"meta":null,"sourceSpan":{"end":[184,8],"start":[172,3]}},"binds":[{"annotation":{"meta":null,"sourceSpan":{"end":[173,39],"start":[173,5]}},"bindType":"NonRec","expression":{"abstraction":{"abstraction":{"annotation":{"meta":null,"sourceSpan":{"end":[0,0],"start":[0,0]}},"type":"Var","value":{"identifier":"add","moduleName":["PSD3","Transition","Engine"]}},"annotation":{"meta":null,"sourceSpan":{"end":[173,39],"start":[173,18]}},"argument":{"annotation":{"meta":null,"sourceSpan":{"end":[173,31],"start":[173,18]}},"expression":{"annotation":{"meta":null,"sourceSpan":{"end":[173,23],"start":[173,18]}},"type":"Var","value":{"identifier":"state","sourcePos":[171,1]}},"fieldName":"elapsed","type":"Accessor"},"type":"App"},"annotation":{"meta":null,"sourceSpan":{"end":[173,39],"start":[173,18]}},"argument":{"annotation":{"meta":null,"sourceSpan":{"end":[173,39],"start":[173,34]}},"type":"Var","value":{"identifier":"delta","sourcePos":[171,1]}},"type":"App"},"identifier":"newElapsed"},{"annotation":{"meta":null,"sourceSpan":{"end":[174,70],"start":[174,5]}},"bindType":"NonRec","expression":{"abstraction":{"abstraction":{"annotation":{"meta":null,"sourceSpan":{"end":[0,0],"start":[0,0]}},"type":"Var","value":{"identifier":"max","moduleName":["PSD3","Transition","Engine"]}},"annotation":{"meta":null,"sourceSpan":{"end":[174,31],"start":[174,24]}},"argument":{"annotation":{"meta":null,"sourceSpan":{"end":[174,31],"start":[174,28]}},"type":"Literal","value":{"literalType":"NumberLiteral","value":0}},"type":"App"},"annotation":{"meta":null,"sourceSpan":{"end":[174,70],"start":[174,24]}},"argument":{"abstraction":{"abstraction":{"annotation":{"meta":null,"sourceSpan":{"end":[0,0],"start":[0,0]}},"type":"Var","value":{"identifier":"sub","moduleName":["PSD3","Transition","Engine"]}},"annotation":{"meta":null,"sourceSpan":{"end":[174,69],"start":[174,33]}},"argument":{"annotation":{"meta":null,"sourceSpan":{"end":[174,43],"start":[174,33]}},"type":"Var","value":{"identifier":"newElapsed","sourcePos":[173,5]}},"type":"App"},"annotation":{"meta":null,"sourceSpan":{"end":[174,69],"start":[174,33]}},"argument":{"annotation":{"meta":null,"sourceSpan":{"end":[174,69],"start":[174,46]}},"expression":{"annotation":{"meta":null,"sourceSpan":{"end":[174,69],"start":[174,46]}},"expression":{"annotation":{"meta":null,"sourceSpan":{"end":[174,69],"start":[174,46]}},"expression":{"annotation":{"meta":null,"sourceSpan":{"end":[174,51],"start":[174,46]}},"type":"Var","value":{"identifier":"state","sourcePos":[171,1]}},"fieldName":"spec","type":"Accessor"},"fieldName":"config","type":"Accessor"},"fieldName":"delay","type":"Accessor"},"type":"App"},"type":"App"},"identifier":"effectiveElapsed"},{"annotation":{"meta":null,"sourceSpan":{"end":[175,64],"start":[175,5]}},"bindType":"NonRec","expression":{"abstraction":{"abstraction":{"annotation":{"meta":null,"sourceSpan":{"end":[0,0],"start":[0,0]}},"type":"Var","value":{"identifier":"div","moduleName":["PSD3","Transition","Engine"]}},"annotation":{"meta":null,"sourceSpan":{"end":[175,64],"start":[175,19]}},"argument":{"annotation":{"meta":null,"sourceSpan":{"end":[175,35],"start":[175,19]}},"type":"Var","value":{"identifier":"effectiveElapsed","sourcePos":[174,5]}},"type":"App"},"annotation":{"meta":null,"sourceSpan":{"end":[175,64],"start":[175,19]}},"argument":{"annotation":{"meta":null,"sourceSpan":{"end":[175,64],"start":[175,38]}},"expression":{"annotation":{"meta":null,"sourceSpan":{"end":[175,64],"start":[175,38]}},"expression":{"annotation":{"meta":null,"sourceSpan":{"end":[175,64],"start":[175,38]}},"expression":{"annotation":{"meta":null,"sourceSpan":{"end":[175,43],"start":[175,38]}},"type":"Var","value":{"identifier":"state","sourcePos":[171,1]}},"fieldName":"spec","type":"Accessor"},"fieldName":"config","type":"Accessor"},"fieldName":"duration","type":"Accessor"},"type":"App"},"identifier":"rawProgress"},{"annotation":{"meta":null,"sourceSpan":{"end":[177,51],"start":[177,5]}},"bindType":"NonRec","expression":{"abstraction":{"annotation":{"meta":{"metaType":"IsForeign"},"sourceSpan":{"end":[177,26],"start":[177,16]}},"type":"Var","value":{"identifier":"toFunction","moduleName":["PSD3","Transition","Easing"]}},"annotation":{"meta":null,"sourceSpan":{"end":[177,51],"start":[177,16]}},"argument":{"annotation":{"meta":null,"sourceSpan":{"end":[177,51],"start":[177,27]}},"expression":{"annotation":{"meta":null,"sourceSpan":{"end":[177,51],"start":[177,27]}},"expression":{"annotation":{"meta":null,"sourceSpan":{"end":[177,51],"start":[177,27]}},"expression":{"annotation":{"meta":null,"sourceSpan":{"end":[177,32],"start":[177,27]}},"type":"Var","value":{"identifier":"state","sourcePos":[171,1]}},"fieldName":"spec","type":"Accessor"},"fieldName":"config","type":"Accessor"},"fieldName":"easing","type":"Accessor"},"type":"App"},"identifier":"easingFn"},{"annotation":{"meta":null,"sourceSpan":{"end":[176,52],"start":[176,5]}},"bindType":"NonRec","expression":{"abstraction":{"abstraction":{"annotation":{"meta":null,"sourceSpan":{"end":[0,0],"start":[0,0]}},"type":"Var","value":{"identifier":"min","moduleName":["PSD3","Transition","Engine"]}},"annotation":{"meta":null,"sourceSpan":{"end":[176,30],"start":[176,23]}},"argument":{"annotation":{"meta":null,"sourceSpan":{"end":[176,30],"start":[176,27]}},"type":"Literal","value":{"literalType":"NumberLiteral","value":1}},"type":"App"},"annotation":{"meta":null,"sourceSpan":{"end":[176,52],"start":[176,23]}},"argument":{"abstraction":{"abstraction":{"annotation":{"meta":null,"sourceSpan":{"end":[0,0],"start":[0,0]}},"type":"Var","value":{"identifier":"max","moduleName":["PSD3","Transition","Engine"]}},"annotation":{"meta":null,"sourceSpan":{"end":[176,39],"start":[176,32]}},"argument":{"annotation":{"meta":null,"sourceSpan":{"end":[176,39],"start":[176,36]}},"type":"Literal","value":{"literalType":"NumberLiteral","value":0}},"type":"App"},"annotation":{"meta":null,"sourceSpan":{"end":[176,51],"start":[176,32]}},"argument":{"annotation":{"meta":null,"sourceSpan":{"end":[176,51],"start":[176,40]}},"type":"Var","value":{"identifier":"rawProgress","sourcePos":[175,5]}},"type":"App"},"type":"App"},"identifier":"clampedProgress"},{"annotation":{"meta":null,"sourceSpan":{"end":[178,45],"start":[178,5]}},"bindType":"NonRec","expression":{"abstraction":{"annotation":{"meta":null,"sourceSpan":{"end":[178,29],"start":[178,21]}},"type":"Var","value":{"identifier":"easingFn","sourcePos":[177,5]}},"annotation":{"meta":null,"sourceSpan":{"end":[178,45],"start":[178,21]}},"argument":{"annotation":{"meta":null,"sourceSpan":{"end":[178,45],"start":[178,30]}},"type":"Var","value":{"identifier":"clampedProgress","sourcePos":[176,5]}},"type":"App"},"identifier":"easedProgress"},{"annotation":{"meta":null,"sourceSpan":{"end":[179,82],"start":[179,5]}},"bindType":"NonRec","expression":{"abstraction":{"abstraction":{"abstraction":{"annotation":{"meta":null,"sourceSpan":{"end":[179,38],"start":[179,16]}},"expression":{"annotation":{"meta":null,"sourceSpan":{"end":[179,38],"start":[179,16]}},"expression":{"annotation":{"meta":null,"sourceSpan":{"end":[179,21],"start":[179,16]}},"type":"Var","value":{"identifier":"state","sourcePos":[171,1]}},"fieldName":"spec","type":"Accessor"},"fieldName":"interpolate","type":"Accessor"},"annotation":{"meta":null,"sourceSpan":{"end":[179,54],"start":[179,16]}},"argument":{"annotation":{"meta":null,"sourceSpan":{"end":[179,54],"start":[179,39]}},"expression":{"annotation":{"meta":null,"sourceSpan":{"end":[179,54],"start":[179,39]}},"expression":{"annotation":{"meta":null,"sourceSpan":{"end":[179,44],"start":[179,39]}},"type":"Var","value":{"identifier":"state","sourcePos":[171,1]}},"fieldName":"spec","type":"Accessor"},"fieldName":"from","type":"Accessor"},"type":"App"},"annotation":{"meta":null,"sourceSpan":{"end":[179,68],"start":[179,16]}},"argument":{"annotation":{"meta":null,"sourceSpan":{"end":[179,68],"start":[179,55]}},"expression":{"annotation":{"meta":null,"sourceSpan":{"end":[179,68],"start":[179,55]}},"expression":{"annotation":{"meta":null,"sourceSpan":{"end":[179,60],"start":[179,55]}},"type":"Var","value":{"identifier":"state","sourcePos":[171,1]}},"fieldName":"spec","type":"Accessor"},"fieldName":"to","type":"Accessor"},"type":"App"},"annotation":{"meta":null,"sourceSpan":{"end":[179,82],"start":[179,16]}},"argument":{"annotation":{"meta":null,"sourceSpan":{"end":[179,82],"start":[179,69]}},"type":"Var","value":{"identifier":"easedProgress","sourcePos":[178,5]}},"type":"App"},"identifier":"newValue"}],"expression":{"annotation":{"meta":null,"sourceSpan":{"end":[184,8],"start":[181,5]}},"binds":[{"annotation":{"meta":null,"sourceSpan":{"end":[184,8],"start":[171,1]}},"bindType":"NonRec","expression":{"annotation":{"meta":null,"sourceSpan":{"end":[181,10],"start":[181,5]}},"type":"Var","value":{"identifier":"state","sourcePos":[171,1]}},"identifier":"v"}],"expression":{"annotation":{"meta":null,"sourceSpan":{"end":[184,8],"start":[181,5]}},"copy":["spec"],"expression":{"annotation":{"meta":null,"sourceSpan":{"end":[0,0],"start":[0,0]}},"type":"Var","value":{"identifier":"v","sourcePos":[171,1]}},"type":"ObjectUpdate","updates":[["elapsed",{"annotation":{"meta":null,"sourceSpan":{"end":[182,29],"start":[182,19]}},"type":"Var","value":{"identifier":"newElapsed","sourcePos":[173,5]}}],["current",{"annotation":{"meta":null,"sourceSpan":{"end":[183,27],"start":[183,19]}},"type":"Var","value":{"identifier":"newValue","sourcePos":[179,5]}}]]},"type":"Let"},"type":"Let"},"type":"Abs"},"type":"Abs"},"identifier":"tickBy"},{"annotation":{"meta":null,"sourceSpan":{"end":[165,73],"start":[165,1]}},"bindType":"NonRec","expression":{"annotation":{"meta":null,"sourceSpan":{"end":[165,73],"start":[165,1]}},"argument":"delta","body":{"annotation":{"meta":null,"sourceSpan":{"end":[165,73],"start":[165,1]}},"argument":"state","body":{"abstraction":{"abstraction":{"annotation":{"meta":null,"sourceSpan":{"end":[166,26],"start":[166,20]}},"type":"Var","value":{"identifier":"tickBy","moduleName":["PSD3","Transition","Engine"]}},"annotation":{"meta":null,"sourceSpan":{"end":[166,32],"start":[166,20]}},"argument":{"annotation":{"meta":null,"sourceSpan":{"end":[166,32],"start":[166,27]}},"type":"Var","value":{"identifier":"delta","sourcePos":[166,1]}},"type":"App"},"annotation":{"meta":null,"sourceSpan":{"end":[166,38],"start":[166,20]}},"argument":{"annotation":{"meta":null,"sourceSpan":{"end":[166,38],"start":[166,33]}},"type":"Var","value":{"identifier":"state","sourcePos":[166,1]}},"type":"App"},"type":"Abs"},"type":"Abs"},"identifier":"tick"},{"annotation":{"meta":null,"sourceSpan":{"end":[157,57],"start":[157,1]}},"bindType":"NonRec","expression":{"annotation":{"meta":null,"sourceSpan":{"end":[157,57],"start":[157,1]}},"argument":"spec","body":{"annotation":{"meta":null,"sourceSpan":{"end":[162,4],"start":[159,3]}},"type":"Literal","value":{"literalType":"ObjectLiteral","value":[["spec",{"annotation":{"meta":null,"sourceSpan":{"end":[159,9],"start":[159,5]}},"type":"Var","value":{"identifier":"spec","sourcePos":[158,1]}}],["elapsed",{"annotation":{"meta":null,"sourceSpan":{"end":[160,17],"start":[160,14]}},"type":"Literal","value":{"literalType":"NumberLiteral","value":0}}],["current",{"annotation":{"meta":null,"sourceSpan":{"end":[161,23],"start":[161,14]}},"expression":{"annotation":{"meta":null,"sourceSpan":{"end":[161,18],"start":[161,14]}},"type":"Var","value":{"identifier":"spec","sourcePos":[158,1]}},"fieldName":"from","type":"Accessor"}]]}},"type":"Abs"},"identifier":"start"},{"annotation":{"meta":null,"sourceSpan":{"end":[262,35],"start":[258,1]}},"bindType":"NonRec","expression":{"annotation":{"meta":null,"sourceSpan":{"end":[262,35],"start":[258,1]}},"argument":"count","body":{"annotation":{"meta":null,"sourceSpan":{"end":[262,35],"start":[258,1]}},"argument":"staggerDelay","body":{"annotation":{"meta":null,"sourceSpan":{"end":[262,35],"start":[258,1]}},"argument":"baseSpec","body":{"annotation":{"meta":{"metaType":"IsWhere"},"sourceSpan":{"end":[264,32],"start":[264,3]}},"binds":[{"annotation":{"meta":null,"sourceSpan":{"end":[266,43],"start":[266,5]}},"bindType":"NonRec","expression":{"annotation":{"meta":null,"sourceSpan":{"end":[266,43],"start":[266,5]}},"argument":"i","body":{"annotation":{"meta":null,"sourceSpan":{"end":[269,65],"start":[268,7]}},"binds":[{"annotation":{"meta":null,"sourceSpan":{"end":[268,49],"start":[268,11]}},"bindType":"NonRec","expression":{"abstraction":{"abstraction":{"annotation":{"meta":null,"sourceSpan":{"end":[0,0],"start":[0,0]}},"type":"Var","value":{"identifier":"mul","moduleName":["PSD3","Transition","Engine"]}},"annotation":{"meta":null,"sourceSpan":{"end":[268,49],"start":[268,24]}},"argument":{"abstraction":{"annotation":{"meta":{"metaType":"IsForeign"},"sourceSpan":{"end":[268,32],"start":[268,24]}},"type":"Var","value":{"identifier":"toNumber","moduleName":["Data","Int"]}},"annotation":{"meta":null,"sourceSpan":{"end":[268,34],"start":[268,24]}},"argument":{"annotation":{"meta":null,"sourceSpan":{"end":[268,34],"start":[268,33]}},"type":"Var","value":{"identifier":"i","sourcePos":[267,5]}},"type":"App"},"type":"App"},"annotation":{"meta":null,"sourceSpan":{"end":[268,49],"start":[268,24]}},"argument":{"annotation":{"meta":null,"sourceSpan":{"end":[268,49],"start":[268,37]}},"type":"Var","value":{"identifier":"staggerDelay","sourcePos":[263,1]}},"type":"App"},"identifier":"indexDelay"}],"expression":{"abstraction":{"abstraction":{"annotation":{"meta":null,"sourceSpan":{"end":[269,19],"start":[269,10]}},"type":"Var","value":{"identifier":"withDelay","moduleName":["PSD3","Transition","Engine"]}},"annotation":{"meta":null,"sourceSpan":{"end":[269,56],"start":[269,10]}},"argument":{"abstraction":{"abstraction":{"annotation":{"meta":null,"sourceSpan":{"end":[0,0],"start":[0,0]}},"type":"Var","value":{"identifier":"add","moduleName":["PSD3","Transition","Engine"]}},"annotation":{"meta":null,"sourceSpan":{"end":[269,55],"start":[269,21]}},"argument":{"annotation":{"meta":null,"sourceSpan":{"end":[269,42],"start":[269,21]}},"expression":{"annotation":{"meta":null,"sourceSpan":{"end":[269,42],"start":[269,21]}},"expression":{"annotation":{"meta":null,"sourceSpan":{"end":[269,29],"start":[269,21]}},"type":"Var","value":{"identifier":"baseSpec","sourcePos":[263,1]}},"fieldName":"config","type":"Accessor"},"fieldName":"delay","type":"Accessor"},"type":"App"},"annotation":{"meta":null,"sourceSpan":{"end":[269,55],"start":[269,21]}},"argument":{"annotation":{"meta":null,"sourceSpan":{"end":[269,55],"start":[269,45]}},"type":"Var","value":{"identifier":"indexDelay","sourcePos":[268,11]}},"type":"App"},"type":"App"},"annotation":{"meta":null,"sourceSpan":{"end":[269,65],"start":[269,10]}},"argument":{"annotation":{"meta":null,"sourceSpan":{"end":[269,65],"start":[269,57]}},"type":"Var","value":{"identifier":"baseSpec","sourcePos":[263,1]}},"type":"App"},"type":"Let"},"type":"Abs"},"identifier":"mkSpec"}],"expression":{"abstraction":{"abstraction":{"annotation":{"meta":null,"sourceSpan":{"end":[0,0],"start":[0,0]}},"type":"Var","value":{"identifier":"map","moduleName":["PSD3","Transition","Engine"]}},"annotation":{"meta":null,"sourceSpan":{"end":[264,13],"start":[264,3]}},"argument":{"annotation":{"meta":null,"sourceSpan":{"end":[264,13],"start":[264,7]}},"type":"Var","value":{"identifier":"mkSpec","sourcePos":[266,5]}},"type":"App"},"annotation":{"meta":null,"sourceSpan":{"end":[264,32],"start":[264,3]}},"argument":{"abstraction":{"abstraction":{"annotation":{"meta":{"metaType":"IsForeign"},"sourceSpan":{"end":[264,19],"start":[264,17]}},"type":"Var","value":{"identifier":"range","moduleName":["Data","Array"]}},"annotation":{"meta":null,"sourceSpan":{"end":[264,31],"start":[264,15]}},"argument":{"annotation":{"meta":null,"sourceSpan":{"end":[264,16],"start":[264,15]}},"type":"Literal","value":{"literalType":"IntLiteral","value":0}},"type":"App"},"annotation":{"meta":null,"sourceSpan":{"end":[264,31],"start":[264,15]}},"argument":{"abstraction":{"abstraction":{"annotation":{"meta":null,"sourceSpan":{"end":[0,0],"start":[0,0]}},"type":"Var","value":{"identifier":"sub1","moduleName":["PSD3","Transition","Engine"]}},"annotation":{"meta":null,"sourceSpan":{"end":[264,30],"start":[264,21]}},"argument":{"annotation":{"meta":null,"sourceSpan":{"end":[264,26],"start":[264,21]}},"type":"Var","value":{"identifier":"count","sourcePos":[263,1]}},"type":"App"},"annotation":{"meta":null,"sourceSpan":{"end":[264,30],"start":[264,21]}},"argument":{"annotation":{"meta":null,"sourceSpan":{"end":[264,30],"start":[264,29]}},"type":"Literal","value":{"literalType":"IntLiteral","value":1}},"type":"App"},"type":"App"},"type":"App"},"type":"Let"},"type":"Abs"},"type":"Abs"},"type":"Abs"},"identifier":"staggeredSpecs"},{"annotation":{"meta":null,"sourceSpan":{"end":[314,28],"start":[310,1]}},"bindType":"NonRec","expression":{"annotation":{"meta":null,"sourceSpan":{"end":[314,28],"start":[310,1]}},"argument":"valuePairs","body":{"annotation":{"meta":null,"sourceSpan":{"end":[314,28],"start":[310,1]}},"argument":"staggerDelay","body":{"annotation":{"meta":null,"sourceSpan":{"end":[314,28],"start":[310,1]}},"argument":"opts","body":{"annotation":{"meta":{"metaType":"IsWhere"},"sourceSpan":{"end":[316,79],"start":[316,3]}},"binds":[{"annotation":{"meta":null,"sourceSpan":{"end":[318,81],"start":[318,5]}},"bindType":"NonRec","expression":{"annotation":{"meta":null,"sourceSpan":{"end":[318,81],"start":[318,5]}},"argument":"i","body":{"annotation":{"meta":null,"sourceSpan":{"end":[318,81],"start":[318,5]}},"argument":"values","body":{"annotation":{"meta":null,"sourceSpan":{"end":[324,48],"start":[320,7]}},"binds":[{"annotation":{"meta":null,"sourceSpan":{"end":[322,38],"start":[322,9]}},"bindType":"NonRec","expression":{"abstraction":{"abstraction":{"annotation":{"meta":null,"sourceSpan":{"end":[322,26],"start":[322,16]}},"type":"Var","value":{"identifier":"transition","moduleName":["PSD3","Transition","Engine"]}},"annotation":{"meta":null,"sourceSpan":{"end":[322,33],"start":[322,16]}},"argument":{"annotation":{"meta":null,"sourceSpan":{"end":[322,33],"start":[322,27]}},"type":"Var","value":{"identifier":"values","sourcePos":[319,5]}},"type":"App"},"annotation":{"meta":null,"sourceSpan":{"end":[322,38],"start":[322,16]}},"argument":{"annotation":{"meta":null,"sourceSpan":{"end":[322,38],"start":[322,34]}},"type":"Var","value":{"identifier":"opts","sourcePos":[315,1]}},"type":"App"},"identifier":"spec"},{"annotation":{"meta":null,"sourceSpan":{"end":[321,47],"start":[321,9]}},"bindType":"NonRec","expression":{"abstraction":{"abstraction":{"annotation":{"meta":null,"sourceSpan":{"end":[0,0],"start":[0,0]}},"type":"Var","value":{"identifier":"mul","moduleName":["PSD3","Transition","Engine"]}},"annotation":{"meta":null,"sourceSpan":{"end":[321,47],"start":[321,22]}},"argument":{"abstraction":{"annotation":{"meta":{"metaType":"IsForeign"},"sourceSpan":{"end":[321,30],"start":[321,22]}},"type":"Var","value":{"identifier":"toNumber","moduleName":["Data","Int"]}},"annotation":{"meta":null,"sourceSpan":{"end":[321,32],"start":[321,22]}},"argument":{"annotation":{"meta":null,"sourceSpan":{"end":[321,32],"start":[321,31]}},"type":"Var","value":{"identifier":"i","sourcePos":[319,5]}},"type":"App"},"type":"App"},"annotation":{"meta":null,"sourceSpan":{"end":[321,47],"start":[321,22]}},"argument":{"annotation":{"meta":null,"sourceSpan":{"end":[321,47],"start":[321,35]}},"type":"Var","value":{"identifier":"staggerDelay","sourcePos":[315,1]}},"type":"App"},"identifier":"indexDelay"},{"annotation":{"meta":null,"sourceSpan":{"end":[323,48],"start":[323,9]}},"bindType":"NonRec","expression":{"abstraction":{"abstraction":{"annotation":{"meta":null,"sourceSpan":{"end":[323,32],"start":[323,23]}},"type":"Var","value":{"identifier":"withDelay","moduleName":["PSD3","Transition","Engine"]}},"annotation":{"meta":null,"sourceSpan":{"end":[323,43],"start":[323,23]}},"argument":{"annotation":{"meta":null,"sourceSpan":{"end":[323,43],"start":[323,33]}},"type":"Var","value":{"identifier":"indexDelay","sourcePos":[321,9]}},"type":"App"},"annotation":{"meta":null,"sourceSpan":{"end":[323,48],"start":[323,23]}},"argument":{"annotation":{"meta":null,"sourceSpan":{"end":[323,48],"start":[323,44]}},"type":"Var","value":{"identifier":"spec","sourcePos":[322,9]}},"type":"App"},"identifier":"delayedSpec"}],"expression":{"annotation":{"meta":null,"sourceSpan":{"end":[324,48],"start":[324,10]}},"type":"Literal","value":{"literalType":"ObjectLiteral","value":[["index",{"annotation":{"meta":null,"sourceSpan":{"end":[324,20],"start":[324,19]}},"type":"Var","value":{"identifier":"i","sourcePos":[319,5]}}],["state",{"abstraction":{"annotation":{"meta":null,"sourceSpan":{"end":[324,34],"start":[324,29]}},"type":"Var","value":{"identifier":"start","moduleName":["PSD3","Transition","Engine"]}},"annotation":{"meta":null,"sourceSpan":{"end":[324,46],"start":[324,29]}},"argument":{"annotation":{"meta":null,"sourceSpan":{"end":[324,46],"start":[324,35]}},"type":"Var","value":{"identifier":"delayedSpec","sourcePos":[323,9]}},"type":"App"}]]}},"type":"Let"},"type":"Abs"},"type":"Abs"},"identifier":"mkTransition"}],"expression":{"abstraction":{"annotation":{"meta":{"metaType":"IsNewtype"},"sourceSpan":{"end":[316,25],"start":[316,3]}},"type":"Var","value":{"identifier":"IndexedTransitionGroup","moduleName":["PSD3","Transition","Engine"]}},"annotation":{"meta":null,"sourceSpan":{"end":[316,79],"start":[316,3]}},"argument":{"annotation":{"meta":null,"sourceSpan":{"end":[316,79],"start":[316,26]}},"type":"Literal","value":{"literalType":"ObjectLiteral","value":[["transitions",{"abstraction":{"abstraction":{"annotation":{"meta":{"metaType":"IsForeign"},"sourceSpan":{"end":[316,53],"start":[316,41]}},"type":"Var","value":{"identifier":"mapWithIndex","moduleName":["Data","Array"]}},"annotation":{"meta":null,"sourceSpan":{"end":[316,66],"start":[316,41]}},"argument":{"annotation":{"meta":null,"sourceSpan":{"end":[316,66],"start":[316,54]}},"type":"Var","value":{"identifier":"mkTransition","sourcePos":[318,5]}},"type":"App"},"annotation":{"meta":null,"sourceSpan":{"end":[316,77],"start":[316,41]}},"argument":{"annotation":{"meta":null,"sourceSpan":{"end":[316,77],"start":[316,67]}},"type":"Var","value":{"identifier":"valuePairs","sourcePos":[315,1]}},"type":"App"}]]}},"type":"App"},"type":"Let"},"type":"Abs"},"type":"Abs"},"type":"Abs"},"identifier":"staggeredGroupIndexed"},{"annotation":{"meta":null,"sourceSpan":{"end":[285,21],"start":[281,1]}},"bindType":"NonRec","expression":{"annotation":{"meta":null,"sourceSpan":{"end":[285,21],"start":[281,1]}},"argument":"valuePairs","body":{"annotation":{"meta":null,"sourceSpan":{"end":[285,21],"start":[281,1]}},"argument":"staggerDelay","body":{"annotation":{"meta":null,"sourceSpan":{"end":[285,21],"start":[281,1]}},"argument":"opts","body":{"annotation":{"meta":{"metaType":"IsWhere"},"sourceSpan":{"end":[287,72],"start":[287,3]}},"binds":[{"annotation":{"meta":null,"sourceSpan":{"end":[289,86],"start":[289,5]}},"bindType":"NonRec","expression":{"annotation":{"meta":null,"sourceSpan":{"end":[289,86],"start":[289,5]}},"argument":"i","body":{"annotation":{"meta":null,"sourceSpan":{"end":[289,86],"start":[289,5]}},"argument":"values","body":{"annotation":{"meta":null,"sourceSpan":{"end":[295,27],"start":[291,7]}},"binds":[{"annotation":{"meta":null,"sourceSpan":{"end":[293,38],"start":[293,9]}},"bindType":"NonRec","expression":{"abstraction":{"abstraction":{"annotation":{"meta":null,"sourceSpan":{"end":[293,26],"start":[293,16]}},"type":"Var","value":{"identifier":"transition","moduleName":["PSD3","Transition","Engine"]}},"annotation":{"meta":null,"sourceSpan":{"end":[293,33],"start":[293,16]}},"argument":{"annotation":{"meta":null,"sourceSpan":{"end":[293,33],"start":[293,27]}},"type":"Var","value":{"identifier":"values","sourcePos":[290,5]}},"type":"App"},"annotation":{"meta":null,"sourceSpan":{"end":[293,38],"start":[293,16]}},"argument":{"annotation":{"meta":null,"sourceSpan":{"end":[293,38],"start":[293,34]}},"type":"Var","value":{"identifier":"opts","sourcePos":[286,1]}},"type":"App"},"identifier":"spec"},{"annotation":{"meta":null,"sourceSpan":{"end":[292,47],"start":[292,9]}},"bindType":"NonRec","expression":{"abstraction":{"abstraction":{"annotation":{"meta":null,"sourceSpan":{"end":[0,0],"start":[0,0]}},"type":"Var","value":{"identifier":"mul","moduleName":["PSD3","Transition","Engine"]}},"annotation":{"meta":null,"sourceSpan":{"end":[292,47],"start":[292,22]}},"argument":{"abstraction":{"annotation":{"meta":{"metaType":"IsForeign"},"sourceSpan":{"end":[292,30],"start":[292,22]}},"type":"Var","value":{"identifier":"toNumber","moduleName":["Data","Int"]}},"annotation":{"meta":null,"sourceSpan":{"end":[292,32],"start":[292,22]}},"argument":{"annotation":{"meta":null,"sourceSpan":{"end":[292,32],"start":[292,31]}},"type":"Var","value":{"identifier":"i","sourcePos":[290,5]}},"type":"App"},"type":"App"},"annotation":{"meta":null,"sourceSpan":{"end":[292,47],"start":[292,22]}},"argument":{"annotation":{"meta":null,"sourceSpan":{"end":[292,47],"start":[292,35]}},"type":"Var","value":{"identifier":"staggerDelay","sourcePos":[286,1]}},"type":"App"},"identifier":"indexDelay"},{"annotation":{"meta":null,"sourceSpan":{"end":[294,48],"start":[294,9]}},"bindType":"NonRec","expression":{"abstraction":{"abstraction":{"annotation":{"meta":null,"sourceSpan":{"end":[294,32],"start":[294,23]}},"type":"Var","value":{"identifier":"withDelay","moduleName":["PSD3","Transition","Engine"]}},"annotation":{"meta":null,"sourceSpan":{"end":[294,43],"start":[294,23]}},"argument":{"annotation":{"meta":null,"sourceSpan":{"end":[294,43],"start":[294,33]}},"type":"Var","value":{"identifier":"indexDelay","sourcePos":[292,9]}},"type":"App"},"annotation":{"meta":null,"sourceSpan":{"end":[294,48],"start":[294,23]}},"argument":{"annotation":{"meta":null,"sourceSpan":{"end":[294,48],"start":[294,44]}},"type":"Var","value":{"identifier":"spec","sourcePos":[293,9]}},"type":"App"},"identifier":"delayedSpec"}],"expression":{"abstraction":{"annotation":{"meta":null,"sourceSpan":{"end":[295,15],"start":[295,10]}},"type":"Var","value":{"identifier":"start","moduleName":["PSD3","Transition","Engine"]}},"annotation":{"meta":null,"sourceSpan":{"end":[295,27],"start":[295,10]}},"argument":{"annotation":{"meta":null,"sourceSpan":{"end":[295,27],"start":[295,16]}},"type":"Var","value":{"identifier":"delayedSpec","sourcePos":[294,9]}},"type":"App"},"type":"Let"},"type":"Abs"},"type":"Abs"},"identifier":"mkTransition"}],"expression":{"abstraction":{"annotation":{"meta":{"metaType":"IsNewtype"},"sourceSpan":{"end":[287,18],"start":[287,3]}},"type":"Var","value":{"identifier":"TransitionGroup","moduleName":["PSD3","Transition","Engine"]}},"annotation":{"meta":null,"sourceSpan":{"end":[287,72],"start":[287,3]}},"argument":{"annotation":{"meta":null,"sourceSpan":{"end":[287,72],"start":[287,19]}},"type":"Literal","value":{"literalType":"ObjectLiteral","value":[["transitions",{"abstraction":{"abstraction":{"annotation":{"meta":{"metaType":"IsForeign"},"sourceSpan":{"end":[287,46],"start":[287,34]}},"type":"Var","value":{"identifier":"mapWithIndex","moduleName":["Data","Array"]}},"annotation":{"meta":null,"sourceSpan":{"end":[287,59],"start":[287,34]}},"argument":{"annotation":{"meta":null,"sourceSpan":{"end":[287,59],"start":[287,47]}},"type":"Var","value":{"identifier":"mkTransition","sourcePos":[289,5]}},"type":"App"},"annotation":{"meta":null,"sourceSpan":{"end":[287,70],"start":[287,34]}},"argument":{"annotation":{"meta":null,"sourceSpan":{"end":[287,70],"start":[287,60]}},"type":"Var","value":{"identifier":"valuePairs","sourcePos":[286,1]}},"type":"App"}]]}},"type":"App"},"type":"Let"},"type":"Abs"},"type":"Abs"},"type":"Abs"},"identifier":"staggeredGroup"},{"annotation":{"meta":null,"sourceSpan":{"end":[205,57],"start":[205,1]}},"bindType":"NonRec","expression":{"annotation":{"meta":null,"sourceSpan":{"end":[205,57],"start":[205,1]}},"argument":"state","body":{"abstraction":{"abstraction":{"annotation":{"meta":null,"sourceSpan":{"end":[0,0],"start":[0,0]}},"type":"Var","value":{"identifier":"max","moduleName":["PSD3","Transition","Engine"]}},"annotation":{"meta":null,"sourceSpan":{"end":[207,10],"start":[207,3]}},"argument":{"annotation":{"meta":null,"sourceSpan":{"end":[207,10],"start":[207,7]}},"type":"Literal","value":{"literalType":"NumberLiteral","value":0}},"type":"App"},"annotation":{"meta":null,"sourceSpan":{"end":[207,81],"start":[207,3]}},"argument":{"abstraction":{"abstraction":{"annotation":{"meta":null,"sourceSpan":{"end":[0,0],"start":[0,0]}},"type":"Var","value":{"identifier":"sub","moduleName":["PSD3","Transition","Engine"]}},"annotation":{"meta":null,"sourceSpan":{"end":[207,80],"start":[207,12]}},"argument":{"abstraction":{"abstraction":{"annotation":{"meta":null,"sourceSpan":{"end":[0,0],"start":[0,0]}},"type":"Var","value":{"identifier":"add","moduleName":["PSD3","Transition","Engine"]}},"annotation":{"meta":null,"sourceSpan":{"end":[207,80],"start":[207,12]}},"argument":{"annotation":{"meta":null,"sourceSpan":{"end":[207,38],"start":[207,12]}},"expression":{"annotation":{"meta":null,"sourceSpan":{"end":[207,38],"start":[207,12]}},"expression":{"annotation":{"meta":null,"sourceSpan":{"end":[207,38],"start":[207,12]}},"expression":{"annotation":{"meta":null,"sourceSpan":{"end":[207,17],"start":[207,12]}},"type":"Var","value":{"identifier":"state","sourcePos":[206,1]}},"fieldName":"spec","type":"Accessor"},"fieldName":"config","type":"Accessor"},"fieldName":"duration","type":"Accessor"},"type":"App"},"annotation":{"meta":null,"sourceSpan":{"end":[207,80],"start":[207,12]}},"argument":{"annotation":{"meta":null,"sourceSpan":{"end":[207,64],"start":[207,41]}},"expression":{"annotation":{"meta":null,"sourceSpan":{"end":[207,64],"start":[207,41]}},"expression":{"annotation":{"meta":null,"sourceSpan":{"end":[207,64],"start":[207,41]}},"expression":{"annotation":{"meta":null,"sourceSpan":{"end":[207,46],"start":[207,41]}},"type":"Var","value":{"identifier":"state","sourcePos":[206,1]}},"fieldName":"spec","type":"Accessor"},"fieldName":"config","type":"Accessor"},"fieldName":"delay","type":"Accessor"},"type":"App"},"type":"App"},"annotation":{"meta":null,"sourceSpan":{"end":[207,80],"start":[207,12]}},"argument":{"annotation":{"meta":null,"sourceSpan":{"end":[207,80],"start":[207,67]}},"expression":{"annotation":{"meta":null,"sourceSpan":{"end":[207,72],"start":[207,67]}},"type":"Var","value":{"identifier":"state","sourcePos":[206,1]}},"fieldName":"elapsed","type":"Accessor"},"type":"App"},"type":"App"},"type":"Abs"},"identifier":"remaining"},{"annotation":{"meta":null,"sourceSpan":{"end":[200,53],"start":[200,1]}},"bindType":"NonRec","expression":{"annotation":{"meta":null,"sourceSpan":{"end":[200,53],"start":[200,1]}},"argument":"state","body":{"abstraction":{"abstraction":{"annotation":{"meta":null,"sourceSpan":{"end":[0,0],"start":[0,0]}},"type":"Var","value":{"identifier":"greaterThanOrEq","moduleName":["PSD3","Transition","Engine"]}},"annotation":{"meta":null,"sourceSpan":{"end":[202,74],"start":[202,3]}},"argument":{"annotation":{"meta":null,"sourceSpan":{"end":[202,16],"start":[202,3]}},"expression":{"annotation":{"meta":null,"sourceSpan":{"end":[202,8],"start":[202,3]}},"type":"Var","value":{"identifier":"state","sourcePos":[201,1]}},"fieldName":"elapsed","type":"Accessor"},"type":"App"},"annotation":{"meta":null,"sourceSpan":{"end":[202,74],"start":[202,3]}},"argument":{"abstraction":{"abstraction":{"annotation":{"meta":null,"sourceSpan":{"end":[0,0],"start":[0,0]}},"type":"Var","value":{"identifier":"add","moduleName":["PSD3","Transition","Engine"]}},"annotation":{"meta":null,"sourceSpan":{"end":[202,73],"start":[202,21]}},"argument":{"annotation":{"meta":null,"sourceSpan":{"end":[202,47],"start":[202,21]}},"expression":{"annotation":{"meta":null,"sourceSpan":{"end":[202,47],"start":[202,21]}},"expression":{"annotation":{"meta":null,"sourceSpan":{"end":[202,47],"start":[202,21]}},"expression":{"annotation":{"meta":null,"sourceSpan":{"end":[202,26],"start":[202,21]}},"type":"Var","value":{"identifier":"state","sourcePos":[201,1]}},"fieldName":"spec","type":"Accessor"},"fieldName":"config","type":"Accessor"},"fieldName":"duration","type":"Accessor"},"type":"App"},"annotation":{"meta":null,"sourceSpan":{"end":[202,73],"start":[202,21]}},"argument":{"annotation":{"meta":null,"sourceSpan":{"end":[202,73],"start":[202,50]}},"expression":{"annotation":{"meta":null,"sourceSpan":{"end":[202,73],"start":[202,50]}},"expression":{"annotation":{"meta":null,"sourceSpan":{"end":[202,73],"start":[202,50]}},"expression":{"annotation":{"meta":null,"sourceSpan":{"end":[202,55],"start":[202,50]}},"type":"Var","value":{"identifier":"state","sourcePos":[201,1]}},"fieldName":"spec","type":"Accessor"},"fieldName":"config","type":"Accessor"},"fieldName":"delay","type":"Accessor"},"type":"App"},"type":"App"},"type":"Abs"},"identifier":"isComplete"},{"annotation":{"meta":null,"sourceSpan":{"end":[327,85],"start":[327,1]}},"bindType":"NonRec","expression":{"annotation":{"meta":null,"sourceSpan":{"end":[327,85],"start":[327,1]}},"argument":"delta","body":{"annotation":{"meta":null,"sourceSpan":{"end":[327,85],"start":[327,1]}},"argument":"v","body":{"annotation":{"meta":null,"sourceSpan":{"end":[327,85],"start":[327,1]}},"caseAlternatives":[{"binders":[{"annotation":{"meta":null,"sourceSpan":{"end":[328,23],"start":[328,18]}},"binderType":"VarBinder","identifier":"delta1"},{"annotation":{"meta":{"metaType":"IsNewtype"},"sourceSpan":{"end":[328,49],"start":[328,25]}},"binderType":"ConstructorBinder","binders":[{"annotation":{"meta":null,"sourceSpan":{"end":[328,49],"start":[328,48]}},"binderType":"VarBinder","identifier":"g"}],"constructorName":{"identifier":"IndexedTransitionGroup","moduleName":["PSD3","Transition","Engine"]},"typeName":{"identifier":"IndexedTransitionGroup","moduleName":["PSD3","Transition","Engine"]}}],"expression":{"annotation":{"meta":{"metaType":"IsWhere"},"sourceSpan":{"end":[330,4],"start":[328,53]}},"binds":[{"annotation":{"meta":null,"sourceSpan":{"end":[332,58],"start":[332,5]}},"bindType":"NonRec","expression":{"annotation":{"meta":null,"sourceSpan":{"end":[332,58],"start":[332,5]}},"argument":"t","body":{"annotation":{"meta":null,"sourceSpan":{"end":[333,53],"start":[333,21]}},"binds":[{"annotation":{"meta":null,"sourceSpan":{"end":[333,53],"start":[328,1]}},"bindType":"NonRec","expression":{"annotation":{"meta":null,"sourceSpan":{"end":[333,22],"start":[333,21]}},"type":"Var","value":{"identifier":"t","sourcePos":[333,5]}},"identifier":"v1"}],"expression":{"annotation":{"meta":null,"sourceSpan":{"end":[333,53],"start":[333,21]}},"copy":["index"],"expression":{"annotation":{"meta":null,"sourceSpan":{"end":[0,0],"start":[0,0]}},"type":"Var","value":{"identifier":"v1","sourcePos":[328,1]}},"type":"ObjectUpdate","updates":[["state",{"abstraction":{"abstraction":{"annotation":{"meta":null,"sourceSpan":{"end":[333,37],"start":[333,33]}},"type":"Var","value":{"identifier":"tick","moduleName":["PSD3","Transition","Engine"]}},"annotation":{"meta":null,"sourceSpan":{"end":[333,43],"start":[333,33]}},"argument":{"annotation":{"meta":null,"sourceSpan":{"end":[333,43],"start":[333,38]}},"type":"Var","value":{"identifier":"delta1","sourcePos":[328,18]}},"type":"App"},"annotation":{"meta":null,"sourceSpan":{"end":[333,51],"start":[333,33]}},"argument":{"annotation":{"meta":null,"sourceSpan":{"end":[333,51],"start":[333,44]}},"expression":{"annotation":{"meta":null,"sourceSpan":{"end":[333,45],"start":[333,44]}},"type":"Var","value":{"identifier":"t","sourcePos":[333,5]}},"fieldName":"state","type":"Accessor"},"type":"App"}]]},"type":"Let"},"type":"Abs"},"identifier":"tickIndexed"}],"expression":{"abstraction":{"annotation":{"meta":{"metaType":"IsNewtype"},"sourceSpan":{"end":[328,75],"start":[328,53]}},"type":"Var","value":{"identifier":"IndexedTransitionGroup","moduleName":["PSD3","Transition","Engine"]}},"annotation":{"meta":null,"sourceSpan":{"end":[330,4],"start":[328,53]}},"argument":{"annotation":{"meta":null,"sourceSpan":{"end":[330,4],"start":[329,3]}},"type":"Literal","value":{"literalType":"ObjectLiteral","value":[["transitions",{"abstraction":{"abstraction":{"annotation":{"meta":null,"sourceSpan":{"end":[0,0],"start":[0,0]}},"type":"Var","value":{"identifier":"map","moduleName":["PSD3","Transition","Engine"]}},"annotation":{"meta":null,"sourceSpan":{"end":[329,33],"start":[329,18]}},"argument":{"annotation":{"meta":null,"sourceSpan":{"end":[329,33],"start":[329,22]}},"type":"Var","value":{"identifier":"tickIndexed","sourcePos":[332,5]}},"type":"App"},"annotation":{"meta":null,"sourceSpan":{"end":[329,47],"start":[329,18]}},"argument":{"annotation":{"meta":null,"sourceSpan":{"end":[329,47],"start":[329,34]}},"expression":{"annotation":{"meta":null,"sourceSpan":{"end":[329,35],"start":[329,34]}},"type":"Var","value":{"identifier":"g","sourcePos":[328,48]}},"fieldName":"transitions","type":"Accessor"},"type":"App"}]]}},"type":"App"},"type":"Let"},"isGuarded":false}],"caseExpressions":[{"annotation":{"meta":null,"sourceSpan":{"end":[333,53],"start":[328,1]}},"type":"Var","value":{"identifier":"delta","sourcePos":[328,18]}},{"annotation":{"meta":null,"sourceSpan":{"end":[333,53],"start":[328,1]}},"type":"Var","value":{"identifier":"v","sourcePos":[0,0]}}],"type":"Case"},"type":"Abs"},"type":"Abs"},"identifier":"indexedGroupTick"},{"annotation":{"meta":null,"sourceSpan":{"end":[346,64],"start":[346,1]}},"bindType":"NonRec","expression":{"annotation":{"meta":null,"sourceSpan":{"end":[346,64],"start":[346,1]}},"argument":"v","body":{"annotation":{"meta":null,"sourceSpan":{"end":[346,64],"start":[346,1]}},"caseAlternatives":[{"binders":[{"annotation":{"meta":{"metaType":"IsNewtype"},"sourceSpan":{"end":[347,48],"start":[347,24]}},"binderType":"ConstructorBinder","binders":[{"annotation":{"meta":null,"sourceSpan":{"end":[347,48],"start":[347,47]}},"binderType":"VarBinder","identifier":"g"}],"constructorName":{"identifier":"IndexedTransitionGroup","moduleName":["PSD3","Transition","Engine"]},"typeName":{"identifier":"IndexedTransitionGroup","moduleName":["PSD3","Transition","Engine"]}}],"expression":{"abstraction":{"abstraction":{"annotation":{"meta":{"metaType":"IsForeign"},"sourceSpan":{"end":[348,12],"start":[348,3]}},"type":"Var","value":{"identifier":"fromMaybe","moduleName":["Data","Maybe"]}},"annotation":{"meta":null,"sourceSpan":{"end":[348,16],"start":[348,3]}},"argument":{"annotation":{"meta":null,"sourceSpan":{"end":[348,16],"start":[348,13]}},"type":"Literal","value":{"literalType":"NumberLiteral","value":0}},"type":"App"},"annotation":{"meta":null,"sourceSpan":{"end":[348,72],"start":[348,3]}},"argument":{"abstraction":{"annotation":{"meta":null,"sourceSpan":{"end":[0,0],"start":[0,0]}},"type":"Var","value":{"identifier":"maximum","moduleName":["PSD3","Transition","Engine"]}},"annotation":{"meta":null,"sourceSpan":{"end":[348,72],"start":[348,3]}},"argument":{"abstraction":{"abstraction":{"annotation":{"meta":null,"sourceSpan":{"end":[0,0],"start":[0,0]}},"type":"Var","value":{"identifier":"map","moduleName":["PSD3","Transition","Engine"]}},"annotation":{"meta":null,"sourceSpan":{"end":[348,58],"start":[348,29]}},"argument":{"annotation":{"meta":null,"sourceSpan":{"end":[348,57],"start":[348,34]}},"argument":"t","body":{"abstraction":{"annotation":{"meta":null,"sourceSpan":{"end":[348,49],"start":[348,40]}},"type":"Var","value":{"identifier":"remaining","moduleName":["PSD3","Transition","Engine"]}},"annotation":{"meta":null,"sourceSpan":{"end":[348,57],"start":[348,40]}},"argument":{"annotation":{"meta":null,"sourceSpan":{"end":[348,57],"start":[348,50]}},"expression":{"annotation":{"meta":null,"sourceSpan":{"end":[348,51],"start":[348,50]}},"type":"Var","value":{"identifier":"t","sourcePos":[348,35]}},"fieldName":"state","type":"Accessor"},"type":"App"},"type":"Abs"},"type":"App"},"annotation":{"meta":null,"sourceSpan":{"end":[348,72],"start":[348,29]}},"argument":{"annotation":{"meta":null,"sourceSpan":{"end":[348,72],"start":[348,59]}},"expression":{"annotation":{"meta":null,"sourceSpan":{"end":[348,60],"start":[348,59]}},"type":"Var","value":{"identifier":"g","sourcePos":[347,47]}},"fieldName":"transitions","type":"Accessor"},"type":"App"},"type":"App"},"type":"App"},"isGuarded":false}],"caseExpressions":[{"annotation":{"meta":null,"sourceSpan":{"end":[348,72],"start":[347,1]}},"type":"Var","value":{"identifier":"v","sourcePos":[0,0]}}],"type":"Case"},"type":"Abs"},"identifier":"indexedGroupRemaining"},{"annotation":{"meta":null,"sourceSpan":{"end":[341,58],"start":[341,1]}},"bindType":"NonRec","expression":{"annotation":{"meta":null,"sourceSpan":{"end":[341,58],"start":[341,1]}},"argument":"v","body":{"annotation":{"meta":null,"sourceSpan":{"end":[341,58],"start":[341,1]}},"caseAlternatives":[{"binders":[{"annotation":{"meta":{"metaType":"IsNewtype"},"sourceSpan":{"end":[342,47],"start":[342,23]}},"binderType":"ConstructorBinder","binders":[{"annotation":{"meta":null,"sourceSpan":{"end":[342,47],"start":[342,46]}},"binderType":"VarBinder","identifier":"g"}],"constructorName":{"identifier":"IndexedTransitionGroup","moduleName":["PSD3","Transition","Engine"]},"typeName":{"identifier":"IndexedTransitionGroup","moduleName":["PSD3","Transition","Engine"]}}],"expression":{"abstraction":{"abstraction":{"annotation":{"meta":null,"sourceSpan":{"end":[0,0],"start":[0,0]}},"type":"Var","value":{"identifier":"all","moduleName":["PSD3","Transition","Engine"]}},"annotation":{"meta":null,"sourceSpan":{"end":[343,33],"start":[343,3]}},"argument":{"annotation":{"meta":null,"sourceSpan":{"end":[343,32],"start":[343,8]}},"argument":"t","body":{"abstraction":{"annotation":{"meta":null,"sourceSpan":{"end":[343,24],"start":[343,14]}},"type":"Var","value":{"identifier":"isComplete","moduleName":["PSD3","Transition","Engine"]}},"annotation":{"meta":null,"sourceSpan":{"end":[343,32],"start":[343,14]}},"argument":{"annotation":{"meta":null,"sourceSpan":{"end":[343,32],"start":[343,25]}},"expression":{"annotation":{"meta":null,"sourceSpan":{"end":[343,26],"start":[343,25]}},"type":"Var","value":{"identifier":"t","sourcePos":[343,9]}},"fieldName":"state","type":"Accessor"},"type":"App"},"type":"Abs"},"type":"App"},"annotation":{"meta":null,"sourceSpan":{"end":[343,47],"start":[343,3]}},"argument":{"annotation":{"meta":null,"sourceSpan":{"end":[343,47],"start":[343,34]}},"expression":{"annotation":{"meta":null,"sourceSpan":{"end":[343,35],"start":[343,34]}},"type":"Var","value":{"identifier":"g","sourcePos":[342,46]}},"fieldName":"transitions","type":"Accessor"},"type":"App"},"isGuarded":false}],"caseExpressions":[{"annotation":{"meta":null,"sourceSpan":{"end":[343,47],"start":[342,1]}},"type":"Var","value":{"identifier":"v","sourcePos":[0,0]}}],"type":"Case"},"type":"Abs"},"identifier":"indexedGroupComplete"},{"annotation":{"meta":null,"sourceSpan":{"end":[226,64],"start":[226,1]}},"bindType":"NonRec","expression":{"annotation":{"meta":null,"sourceSpan":{"end":[226,64],"start":[226,1]}},"argument":"delta","body":{"annotation":{"meta":null,"sourceSpan":{"end":[226,64],"start":[226,1]}},"argument":"v","body":{"annotation":{"meta":null,"sourceSpan":{"end":[226,64],"start":[226,1]}},"caseAlternatives":[{"binders":[{"annotation":{"meta":null,"sourceSpan":{"end":[227,16],"start":[227,11]}},"binderType":"VarBinder","identifier":"delta1"},{"annotation":{"meta":{"metaType":"IsNewtype"},"sourceSpan":{"end":[227,35],"start":[227,18]}},"binderType":"ConstructorBinder","binders":[{"annotation":{"meta":null,"sourceSpan":{"end":[227,35],"start":[227,34]}},"binderType":"VarBinder","identifier":"g"}],"constructorName":{"identifier":"TransitionGroup","moduleName":["PSD3","Transition","Engine"]},"typeName":{"identifier":"TransitionGroup","moduleName":["PSD3","Transition","Engine"]}}],"expression":{"abstraction":{"annotation":{"meta":{"metaType":"IsNewtype"},"sourceSpan":{"end":[227,54],"start":[227,39]}},"type":"Var","value":{"identifier":"TransitionGroup","moduleName":["PSD3","Transition","Engine"]}},"annotation":{"meta":null,"sourceSpan":{"end":[229,4],"start":[227,39]}},"argument":{"annotation":{"meta":null,"sourceSpan":{"end":[229,4],"start":[228,3]}},"type":"Literal","value":{"literalType":"ObjectLiteral","value":[["transitions",{"abstraction":{"abstraction":{"annotation":{"meta":null,"sourceSpan":{"end":[0,0],"start":[0,0]}},"type":"Var","value":{"identifier":"map","moduleName":["PSD3","Transition","Engine"]}},"annotation":{"meta":null,"sourceSpan":{"end":[228,34],"start":[228,18]}},"argument":{"abstraction":{"annotation":{"meta":null,"sourceSpan":{"end":[228,27],"start":[228,23]}},"type":"Var","value":{"identifier":"tick","moduleName":["PSD3","Transition","Engine"]}},"annotation":{"meta":null,"sourceSpan":{"end":[228,33],"start":[228,23]}},"argument":{"annotation":{"meta":null,"sourceSpan":{"end":[228,33],"start":[228,28]}},"type":"Var","value":{"identifier":"delta1","sourcePos":[227,11]}},"type":"App"},"type":"App"},"annotation":{"meta":null,"sourceSpan":{"end":[228,48],"start":[228,18]}},"argument":{"annotation":{"meta":null,"sourceSpan":{"end":[228,48],"start":[228,35]}},"expression":{"annotation":{"meta":null,"sourceSpan":{"end":[228,36],"start":[228,35]}},"type":"Var","value":{"identifier":"g","sourcePos":[227,34]}},"fieldName":"transitions","type":"Accessor"},"type":"App"}]]}},"type":"App"},"isGuarded":false}],"caseExpressions":[{"annotation":{"meta":null,"sourceSpan":{"end":[229,4],"start":[227,1]}},"type":"Var","value":{"identifier":"delta","sourcePos":[227,11]}},{"annotation":{"meta":null,"sourceSpan":{"end":[229,4],"start":[227,1]}},"type":"Var","value":{"identifier":"v","sourcePos":[0,0]}}],"type":"Case"},"type":"Abs"},"type":"Abs"},"identifier":"groupTick"},{"annotation":{"meta":null,"sourceSpan":{"end":[240,50],"start":[240,1]}},"bindType":"NonRec","expression":{"annotation":{"meta":null,"sourceSpan":{"end":[240,50],"start":[240,1]}},"argument":"v","body":{"annotation":{"meta":null,"sourceSpan":{"end":[240,50],"start":[240,1]}},"caseAlternatives":[{"binders":[{"annotation":{"meta":{"metaType":"IsNewtype"},"sourceSpan":{"end":[241,34],"start":[241,17]}},"binderType":"ConstructorBinder","binders":[{"annotation":{"meta":null,"sourceSpan":{"end":[241,34],"start":[241,33]}},"binderType":"VarBinder","identifier":"g"}],"constructorName":{"identifier":"TransitionGroup","moduleName":["PSD3","Transition","Engine"]},"typeName":{"identifier":"TransitionGroup","moduleName":["PSD3","Transition","Engine"]}}],"expression":{"abstraction":{"abstraction":{"annotation":{"meta":{"metaType":"IsForeign"},"sourceSpan":{"end":[242,12],"start":[242,3]}},"type":"Var","value":{"identifier":"fromMaybe","moduleName":["Data","Maybe"]}},"annotation":{"meta":null,"sourceSpan":{"end":[242,16],"start":[242,3]}},"argument":{"annotation":{"meta":null,"sourceSpan":{"end":[242,16],"start":[242,13]}},"type":"Literal","value":{"literalType":"NumberLiteral","value":0}},"type":"App"},"annotation":{"meta":null,"sourceSpan":{"end":[242,56],"start":[242,3]}},"argument":{"abstraction":{"annotation":{"meta":null,"sourceSpan":{"end":[0,0],"start":[0,0]}},"type":"Var","value":{"identifier":"maximum","moduleName":["PSD3","Transition","Engine"]}},"annotation":{"meta":null,"sourceSpan":{"end":[242,56],"start":[242,3]}},"argument":{"abstraction":{"abstraction":{"annotation":{"meta":null,"sourceSpan":{"end":[0,0],"start":[0,0]}},"type":"Var","value":{"identifier":"map","moduleName":["PSD3","Transition","Engine"]}},"annotation":{"meta":null,"sourceSpan":{"end":[242,42],"start":[242,29]}},"argument":{"annotation":{"meta":null,"sourceSpan":{"end":[242,42],"start":[242,33]}},"type":"Var","value":{"identifier":"remaining","moduleName":["PSD3","Transition","Engine"]}},"type":"App"},"annotation":{"meta":null,"sourceSpan":{"end":[242,56],"start":[242,29]}},"argument":{"annotation":{"meta":null,"sourceSpan":{"end":[242,56],"start":[242,43]}},"expression":{"annotation":{"meta":null,"sourceSpan":{"end":[242,44],"start":[242,43]}},"type":"Var","value":{"identifier":"g","sourcePos":[241,33]}},"fieldName":"transitions","type":"Accessor"},"type":"App"},"type":"App"},"type":"App"},"isGuarded":false}],"caseExpressions":[{"annotation":{"meta":null,"sourceSpan":{"end":[242,56],"start":[241,1]}},"type":"Var","value":{"identifier":"v","sourcePos":[0,0]}}],"type":"Case"},"type":"Abs"},"identifier":"groupRemaining"},{"annotation":{"meta":null,"sourceSpan":{"end":[236,44],"start":[236,1]}},"bindType":"NonRec","expression":{"annotation":{"meta":null,"sourceSpan":{"end":[236,44],"start":[236,1]}},"argument":"v","body":{"annotation":{"meta":null,"sourceSpan":{"end":[236,44],"start":[236,1]}},"caseAlternatives":[{"binders":[{"annotation":{"meta":{"metaType":"IsNewtype"},"sourceSpan":{"end":[237,33],"start":[237,16]}},"binderType":"ConstructorBinder","binders":[{"annotation":{"meta":null,"sourceSpan":{"end":[237,33],"start":[237,32]}},"binderType":"VarBinder","identifier":"g"}],"constructorName":{"identifier":"TransitionGroup","moduleName":["PSD3","Transition","Engine"]},"typeName":{"identifier":"TransitionGroup","moduleName":["PSD3","Transition","Engine"]}}],"expression":{"abstraction":{"abstraction":{"annotation":{"meta":null,"sourceSpan":{"end":[0,0],"start":[0,0]}},"type":"Var","value":{"identifier":"all","moduleName":["PSD3","Transition","Engine"]}},"annotation":{"meta":null,"sourceSpan":{"end":[237,51],"start":[237,37]}},"argument":{"annotation":{"meta":null,"sourceSpan":{"end":[237,51],"start":[237,41]}},"type":"Var","value":{"identifier":"isComplete","moduleName":["PSD3","Transition","Engine"]}},"type":"App"},"annotation":{"meta":null,"sourceSpan":{"end":[237,65],"start":[237,37]}},"argument":{"annotation":{"meta":null,"sourceSpan":{"end":[237,65],"start":[237,52]}},"expression":{"annotation":{"meta":null,"sourceSpan":{"end":[237,53],"start":[237,52]}},"type":"Var","value":{"identifier":"g","sourcePos":[237,32]}},"fieldName":"transitions","type":"Accessor"},"type":"App"},"isGuarded":false}],"caseExpressions":[{"annotation":{"meta":null,"sourceSpan":{"end":[237,65],"start":[237,1]}},"type":"Var","value":{"identifier":"v","sourcePos":[0,0]}}],"type":"Case"},"type":"Abs"},"identifier":"groupComplete"},{"annotation":{"meta":null,"sourceSpan":{"end":[220,58],"start":[220,1]}},"bindType":"NonRec","expression":{"annotation":{"meta":null,"sourceSpan":{"end":[220,58],"start":[220,1]}},"argument":"specs","body":{"abstraction":{"annotation":{"meta":{"metaType":"IsNewtype"},"sourceSpan":{"end":[221,30],"start":[221,15]}},"type":"Var","value":{"identifier":"TransitionGroup","moduleName":["PSD3","Transition","Engine"]}},"annotation":{"meta":null,"sourceSpan":{"end":[223,4],"start":[221,15]}},"argument":{"annotation":{"meta":null,"sourceSpan":{"end":[223,4],"start":[222,3]}},"type":"Literal","value":{"literalType":"ObjectLiteral","value":[["transitions",{"abstraction":{"abstraction":{"annotation":{"meta":null,"sourceSpan":{"end":[0,0],"start":[0,0]}},"type":"Var","value":{"identifier":"map","moduleName":["PSD3","Transition","Engine"]}},"annotation":{"meta":null,"sourceSpan":{"end":[222,27],"start":[222,18]}},"argument":{"annotation":{"meta":null,"sourceSpan":{"end":[222,27],"start":[222,22]}},"type":"Var","value":{"identifier":"start","moduleName":["PSD3","Transition","Engine"]}},"type":"App"},"annotation":{"meta":null,"sourceSpan":{"end":[222,33],"start":[222,18]}},"argument":{"annotation":{"meta":null,"sourceSpan":{"end":[222,33],"start":[222,28]}},"type":"Var","value":{"identifier":"specs","sourcePos":[221,1]}},"type":"App"}]]}},"type":"App"},"type":"Abs"},"identifier":"group"},{"annotation":{"meta":null,"sourceSpan":{"end":[98,34],"start":[98,1]}},"bindType":"NonRec","expression":{"annotation":{"meta":null,"sourceSpan":{"end":[103,4],"start":[100,3]}},"type":"Literal","value":{"literalType":"ObjectLiteral","value":[["duration",{"annotation":{"meta":null,"sourceSpan":{"end":[100,20],"start":[100,15]}},"type":"Literal","value":{"literalType":"NumberLiteral","value":300}}],["easing",{"annotation":{"meta":{"constructorType":"SumType","identifiers":[],"metaType":"IsConstructor"},"sourceSpan":{"end":[101,20],"start":[101,13]}},"type":"Var","value":{"identifier":"QuadOut","moduleName":["PSD3","Transition","Easing"]}}],["delay",{"annotation":{"meta":null,"sourceSpan":{"end":[102,15],"start":[102,12]}},"type":"Literal","value":{"literalType":"NumberLiteral","value":0}}]]}},"identifier":"defaultConfig"},{"annotation":{"meta":null,"sourceSpan":{"end":[187,49],"start":[187,1]}},"bindType":"NonRec","expression":{"annotation":{"meta":null,"sourceSpan":{"end":[188,25],"start":[188,16]}},"argument":"v","body":{"annotation":{"meta":null,"sourceSpan":{"end":[188,25],"start":[188,16]}},"expression":{"annotation":{"meta":null,"sourceSpan":{"end":[0,0],"start":[0,0]}},"type":"Var","value":{"identifier":"v","sourcePos":[0,0]}},"fieldName":"current","type":"Accessor"},"type":"Abs"},"identifier":"currentValue"},{"annotation":{"meta":null,"sourceSpan":{"end":[232,47],"start":[232,1]}},"bindType":"NonRec","expression":{"annotation":{"meta":null,"sourceSpan":{"end":[232,47],"start":[232,1]}},"argument":"v","body":{"annotation":{"meta":null,"sourceSpan":{"end":[232,47],"start":[232,1]}},"caseAlternatives":[{"binders":[{"annotation":{"meta":{"metaType":"IsNewtype"},"sourceSpan":{"end":[233,31],"start":[233,14]}},"binderType":"ConstructorBinder","binders":[{"annotation":{"meta":null,"sourceSpan":{"end":[233,31],"start":[233,30]}},"binderType":"VarBinder","identifier":"g"}],"constructorName":{"identifier":"TransitionGroup","moduleName":["PSD3","Transition","Engine"]},"typeName":{"identifier":"TransitionGroup","moduleName":["PSD3","Transition","Engine"]}}],"expression":{"abstraction":{"abstraction":{"annotation":{"meta":null,"sourceSpan":{"end":[0,0],"start":[0,0]}},"type":"Var","value":{"identifier":"map","moduleName":["PSD3","Transition","Engine"]}},"annotation":{"meta":null,"sourceSpan":{"end":[233,51],"start":[233,35]}},"argument":{"annotation":{"meta":null,"sourceSpan":{"end":[233,51],"start":[233,39]}},"type":"Var","value":{"identifier":"currentValue","moduleName":["PSD3","Transition","Engine"]}},"type":"App"},"annotation":{"meta":null,"sourceSpan":{"end":[233,65],"start":[233,35]}},"argument":{"annotation":{"meta":null,"sourceSpan":{"end":[233,65],"start":[233,52]}},"expression":{"annotation":{"meta":null,"sourceSpan":{"end":[233,53],"start":[233,52]}},"type":"Var","value":{"identifier":"g","sourcePos":[233,30]}},"fieldName":"transitions","type":"Accessor"},"type":"App"},"isGuarded":false}],"caseExpressions":[{"annotation":{"meta":null,"sourceSpan":{"end":[233,65],"start":[233,1]}},"type":"Var","value":{"identifier":"v","sourcePos":[0,0]}}],"type":"Case"},"type":"Abs"},"identifier":"groupValues"},{"annotation":{"meta":null,"sourceSpan":{"end":[336,83],"start":[336,1]}},"bindType":"NonRec","expression":{"annotation":{"meta":null,"sourceSpan":{"end":[336,83],"start":[336,1]}},"argument":"v","body":{"annotation":{"meta":null,"sourceSpan":{"end":[336,83],"start":[336,1]}},"caseAlternatives":[{"binders":[{"annotation":{"meta":{"metaType":"IsNewtype"},"sourceSpan":{"end":[337,40],"start":[337,16]}},"binderType":"ConstructorBinder","binders":[{"annotation":{"meta":null,"sourceSpan":{"end":[337,40],"start":[337,39]}},"binderType":"VarBinder","identifier":"g"}],"constructorName":{"identifier":"IndexedTransitionGroup","moduleName":["PSD3","Transition","Engine"]},"typeName":{"identifier":"IndexedTransitionGroup","moduleName":["PSD3","Transition","Engine"]}}],"expression":{"abstraction":{"abstraction":{"annotation":{"meta":null,"sourceSpan":{"end":[0,0],"start":[0,0]}},"type":"Var","value":{"identifier":"map","moduleName":["PSD3","Transition","Engine"]}},"annotation":{"meta":null,"sourceSpan":{"end":[338,62],"start":[338,3]}},"argument":{"annotation":{"meta":null,"sourceSpan":{"end":[338,61],"start":[338,8]}},"argument":"t","body":{"annotation":{"meta":null,"sourceSpan":{"end":[338,61],"start":[338,14]}},"type":"Literal","value":{"literalType":"ObjectLiteral","value":[["index",{"annotation":{"meta":null,"sourceSpan":{"end":[338,30],"start":[338,23]}},"expression":{"annotation":{"meta":null,"sourceSpan":{"end":[338,24],"start":[338,23]}},"type":"Var","value":{"identifier":"t","sourcePos":[338,9]}},"fieldName":"index","type":"Accessor"}],["value",{"abstraction":{"annotation":{"meta":null,"sourceSpan":{"end":[338,51],"start":[338,39]}},"type":"Var","value":{"identifier":"currentValue","moduleName":["PSD3","Transition","Engine"]}},"annotation":{"meta":null,"sourceSpan":{"end":[338,59],"start":[338,39]}},"argument":{"annotation":{"meta":null,"sourceSpan":{"end":[338,59],"start":[338,52]}},"expression":{"annotation":{"meta":null,"sourceSpan":{"end":[338,53],"start":[338,52]}},"type":"Var","value":{"identifier":"t","sourcePos":[338,9]}},"fieldName":"state","type":"Accessor"},"type":"App"}]]}},"type":"Abs"},"type":"App"},"annotation":{"meta":null,"sourceSpan":{"end":[338,76],"start":[338,3]}},"argument":{"annotation":{"meta":null,"sourceSpan":{"end":[338,76],"start":[338,63]}},"expression":{"annotation":{"meta":null,"sourceSpan":{"end":[338,64],"start":[338,63]}},"type":"Var","value":{"identifier":"g","sourcePos":[337,39]}},"fieldName":"transitions","type":"Accessor"},"type":"App"},"isGuarded":false}],"caseExpressions":[{"annotation":{"meta":null,"sourceSpan":{"end":[338,76],"start":[337,1]}},"type":"Var","value":{"identifier":"v","sourcePos":[0,0]}}],"type":"Case"},"type":"Abs"},"identifier":"indexedValues"},{"annotation":{"meta":null,"sourceSpan":{"end":[191,59],"start":[191,1]}},"bindType":"NonRec","expression":{"annotation":{"meta":null,"sourceSpan":{"end":[191,59],"start":[191,1]}},"argument":"state","body":{"annotation":{"meta":null,"sourceSpan":{"end":[197,26],"start":[193,3]}},"binds":[{"annotation":{"meta":null,"sourceSpan":{"end":[194,73],"start":[194,5]}},"bindType":"NonRec","expression":{"abstraction":{"abstraction":{"annotation":{"meta":null,"sourceSpan":{"end":[0,0],"start":[0,0]}},"type":"Var","value":{"identifier":"max","moduleName":["PSD3","Transition","Engine"]}},"annotation":{"meta":null,"sourceSpan":{"end":[194,31],"start":[194,24]}},"argument":{"annotation":{"meta":null,"sourceSpan":{"end":[194,31],"start":[194,28]}},"type":"Literal","value":{"literalType":"NumberLiteral","value":0}},"type":"App"},"annotation":{"meta":null,"sourceSpan":{"end":[194,73],"start":[194,24]}},"argument":{"abstraction":{"abstraction":{"annotation":{"meta":null,"sourceSpan":{"end":[0,0],"start":[0,0]}},"type":"Var","value":{"identifier":"sub","moduleName":["PSD3","Transition","Engine"]}},"annotation":{"meta":null,"sourceSpan":{"end":[194,72],"start":[194,33]}},"argument":{"annotation":{"meta":null,"sourceSpan":{"end":[194,46],"start":[194,33]}},"expression":{"annotation":{"meta":null,"sourceSpan":{"end":[194,38],"start":[194,33]}},"type":"Var","value":{"identifier":"state","sourcePos":[192,1]}},"fieldName":"elapsed","type":"Accessor"},"type":"App"},"annotation":{"meta":null,"sourceSpan":{"end":[194,72],"start":[194,33]}},"argument":{"annotation":{"meta":null,"sourceSpan":{"end":[194,72],"start":[194,49]}},"expression":{"annotation":{"meta":null,"sourceSpan":{"end":[194,72],"start":[194,49]}},"expression":{"annotation":{"meta":null,"sourceSpan":{"end":[194,72],"start":[194,49]}},"expression":{"annotation":{"meta":null,"sourceSpan":{"end":[194,54],"start":[194,49]}},"type":"Var","value":{"identifier":"state","sourcePos":[192,1]}},"fieldName":"spec","type":"Accessor"},"fieldName":"config","type":"Accessor"},"fieldName":"delay","type":"Accessor"},"type":"App"},"type":"App"},"identifier":"effectiveElapsed"},{"annotation":{"meta":null,"sourceSpan":{"end":[195,56],"start":[195,5]}},"bindType":"NonRec","expression":{"abstraction":{"abstraction":{"annotation":{"meta":null,"sourceSpan":{"end":[0,0],"start":[0,0]}},"type":"Var","value":{"identifier":"div","moduleName":["PSD3","Transition","Engine"]}},"annotation":{"meta":null,"sourceSpan":{"end":[195,56],"start":[195,11]}},"argument":{"annotation":{"meta":null,"sourceSpan":{"end":[195,27],"start":[195,11]}},"type":"Var","value":{"identifier":"effectiveElapsed","sourcePos":[194,5]}},"type":"App"},"annotation":{"meta":null,"sourceSpan":{"end":[195,56],"start":[195,11]}},"argument":{"annotation":{"meta":null,"sourceSpan":{"end":[195,56],"start":[195,30]}},"expression":{"annotation":{"meta":null,"sourceSpan":{"end":[195,56],"start":[195,30]}},"expression":{"annotation":{"meta":null,"sourceSpan":{"end":[195,56],"start":[195,30]}},"expression":{"annotation":{"meta":null,"sourceSpan":{"end":[195,35],"start":[195,30]}},"type":"Var","value":{"identifier":"state","sourcePos":[192,1]}},"fieldName":"spec","type":"Accessor"},"fieldName":"config","type":"Accessor"},"fieldName":"duration","type":"Accessor"},"type":"App"},"identifier":"raw"}],"expression":{"abstraction":{"abstraction":{"annotation":{"meta":null,"sourceSpan":{"end":[0,0],"start":[0,0]}},"type":"Var","value":{"identifier":"min","moduleName":["PSD3","Transition","Engine"]}},"annotation":{"meta":null,"sourceSpan":{"end":[197,12],"start":[197,5]}},"argument":{"annotation":{"meta":null,"sourceSpan":{"end":[197,12],"start":[197,9]}},"type":"Literal","value":{"literalType":"NumberLiteral","value":1}},"type":"App"},"annotation":{"meta":null,"sourceSpan":{"end":[197,26],"start":[197,5]}},"argument":{"abstraction":{"abstraction":{"annotation":{"meta":null,"sourceSpan":{"end":[0,0],"start":[0,0]}},"type":"Var","value":{"identifier":"max","moduleName":["PSD3","Transition","Engine"]}},"annotation":{"meta":null,"sourceSpan":{"end":[197,21],"start":[197,14]}},"argument":{"annotation":{"meta":null,"sourceSpan":{"end":[197,21],"start":[197,18]}},"type":"Literal","value":{"literalType":"NumberLiteral","value":0}},"type":"App"},"annotation":{"meta":null,"sourceSpan":{"end":[197,25],"start":[197,14]}},"argument":{"annotation":{"meta":null,"sourceSpan":{"end":[197,25],"start":[197,22]}},"type":"Var","value":{"identifier":"raw","sourcePos":[195,5]}},"type":"App"},"type":"App"},"type":"Let"},"type":"Abs"},"identifier":"currentProgress"}],"exports":["transition","transitionWith","withDelay","start","tick","tickBy","currentValue","currentProgress","isComplete","remaining","group","groupTick","groupValues","groupComplete","groupRemaining","staggeredGroup","staggeredSpecs","staggeredGroupIndexed","indexedGroupTick","indexedValues","indexedGroupComplete","indexedGroupRemaining","defaultConfig"],"foreign":[],"imports":[{"annotation":{"meta":null,"sourceSpan":{"end":[348,72],"start":[36,1]}},"moduleName":["Data","Array"]},{"annotation":{"meta":null,"sourceSpan":{"end":[348,72],"start":[36,1]}},"moduleName":["Data","EuclideanRing"]},{"annotation":{"meta":null,"sourceSpan":{"end":[348,72],"start":[36,1]}},"moduleName":["Data","Foldable"]},{"annotation":{"meta":null,"sourceSpan":{"end":[348,72],"start":[36,1]}},"moduleName":["Data","Function"]},{"annotation":{"meta":null,"sourceSpan":{"end":[348,72],"start":[36,1]}},"moduleName":["Data","Functor"]},{"annotation":{"meta":null,"sourceSpan":{"end":[348,72],"start":[36,1]}},"moduleName":["Data","HeytingAlgebra"]},{"annotation":{"meta":null,"sourceSpan":{"end":[348,72],"start":[36,1]}},"moduleName":["Data","Int"]},{"annotation":{"meta":null,"sourceSpan":{"end":[348,72],"start":[36,1]}},"moduleName":["Data","Maybe"]},{"annotation":{"meta":null,"sourceSpan":{"end":[348,72],"start":[36,1]}},"moduleName":["Data","Ord"]},{"annotation":{"meta":null,"sourceSpan":{"end":[348,72],"start":[36,1]}},"moduleName":["Data","Ring"]},{"annotation":{"meta":null,"sourceSpan":{"end":[348,72],"start":[36,1]}},"moduleName":["Data","Semiring"]},{"annotation":{"meta":null,"sourceSpan":{"end":[348,72],"start":[36,1]}},"moduleName":["PSD3","Transition","Easing"]},{"annotation":{"meta":null,"sourceSpan":{"end":[348,72],"start":[36,1]}},"moduleName":["PSD3","Transition","Engine"]},{"annotation":{"meta":null,"sourceSpan":{"end":[348,72],"start":[36,1]}},"moduleName":["PSD3","Transition","Tick"]},{"annotation":{"meta":null,"sourceSpan":{"end":[74,15],"start":[74,1]}},"moduleName":["Prelude"]},{"annotation":{"meta":null,"sourceSpan":{"end":[348,72],"start":[36,1]}},"moduleName":["Prim"]}],"moduleName":["PSD3","Transition","Engine"],"modulePath":"../purescript-psd3-simulation/src/PSD3/Transition/Engine.purs","reExports":{},"sourceSpan":{"end":[348,72],"start":[36,1]}}